<?xml version="1.0" encoding="utf-8" standalone="yes"?>
<database application="Hazeron Scouter" version="0.3.3.4">
  <body name="M9 V Main Sequence" sectorname="" sectorcoords="309, 1, 5" systemname="EDIUR" systemcoords="-4.7, -0.8, 0.2" designation="" type="Star" diameter="0.075au" zone="" atmosphere="" timestamp="8/11/2012 8:30:58 PM" outofrange="False">
    <res name="Type M Preons">Q68 5%</res>
  </body>
  <body name="System EDIUR I" sectorname="" sectorcoords="309, 1, 5" systemname="EDIUR" systemcoords="-4.7, -0.8, 0.2" designation="" type="Planet" diameter="18900m" zone="Frigid" atmosphere="Standard" timestamp="8/11/2012 8:30:58 PM" outofrange="False">
    <res name="Bolite">Q133 1%, Q90 1%, Q149 1%</res>
    <res name="Coal">Q172 1%, Q45 1%, Q30 1%</res>
    <res name="Crystals">Q120 1%, Q89 1%, Q106 2%</res>
    <res name="Gems">Q153 1%, Q211 1%, Q187 1%</res>
    <res name="Ice">Q84 46%, Q139 46%, Q240 10%</res>
    <res name="Lumenite">Q79 1%, Q112 1%, Q62 1%</res>
    <res name="Minerals">Q116 1%, Q200 1%, Q206 1%</res>
    <res name="Natural Gas">Q132 2%, Q26 1%, Q190 1%</res>
    <res name="Oil">Q67 2%, Q134 1%, Q61 1%</res>
    <res name="Ore">Q100 1%, Q248 1%, Q122 1%</res>
    <res name="Polytaride">Q154 1%, None, Q80 1%</res>
    <res name="Radioactives">Q129 1%, Q148 1%, Q168 1%</res>
    <res name="Stone">Q7 1%, Q156 1%, Q121 2%</res>
    <res name="Myrathane">Q80 97%</res>
    <res name="Air">Q11 95%</res>
    <res name="Hydrogen">Q60 95%</res>
    <res name="Sunlight">Q140 10%</res>
    <res name="Animal Carcass">Q116, Q114, Q209</res>
    <res name="Beans">Q163, Q141, Q115</res>
    <res name="Cheese">Q189, Q35, Q212</res>
    <res name="Eggs">Q168, Q31, Q162</res>
    <res name="Fertilizer">Q38, Q186, Q113</res>
    <res name="Fruit">Q165, Q123, Q122</res>
    <res name="Grain">Q219, Q125, Q211</res>
    <res name="Grapes">Q211, Q163, Q108</res>
    <res name="Herbs">Q254, Q144, Q227</res>
    <res name="Hops">Q158, Q160, Q155</res>
    <res name="Log">Q131, Q101, Q109</res>
    <res name="Milk">Q220, Q136, Q39</res>
    <res name="Nuts">Q116, Q145, Q66</res>
    <res name="Plant Fiber">Q98, Q121, Q96</res>
    <res name="Spices">Q156, Q30, Q94</res>
    <res name="Vegetable">Q110, Q126, Q86</res>
    <res name="Vegetation Density">Q12, Q151, Q100</res>
  </body>
  <body name="System EDIUR Ia" sectorname="" sectorcoords="309, 1, 5" systemname="EDIUR" systemcoords="-4.7, -0.8, 0.2" designation="" type="Moon" diameter="3800m" zone="Frigid" atmosphere="No Atmosphere" timestamp="8/11/2012 8:30:58 PM" outofrange="False">
    <res name="Coal">Q140 1%</res>
    <res name="Crystals">Q100 1%</res>
    <res name="Eludium">Q203 52%</res>
    <res name="Gems">Q234 1%</res>
    <res name="Ice">Q100 1%</res>
    <res name="Lumenite">Q166 1%</res>
    <res name="Minerals">Q121 1%</res>
    <res name="Natural Gas">Q89 1%</res>
    <res name="Oil">Q105 1%</res>
    <res name="Ore">Q83 1%</res>
    <res name="Radioactives">Q167 1%</res>
    <res name="Stone">Q201 1%</res>
    <res name="Sunlight">Q157 10%</res>
    <res name="Animal Carcass">Q169</res>
    <res name="Beans">Q104</res>
    <res name="Cheese">Q201</res>
    <res name="Eggs">Q223</res>
    <res name="Fertilizer">Q122</res>
    <res name="Fruit">Q136</res>
    <res name="Grain">Q98</res>
    <res name="Grapes">Q180</res>
    <res name="Herbs">Q187</res>
    <res name="Hops">Q208</res>
    <res name="Log">Q37</res>
    <res name="Milk">Q98</res>
    <res name="Nuts">Q147</res>
    <res name="Plant Fiber">Q138</res>
    <res name="Spices">Q219</res>
    <res name="Vegetable">Q168</res>
    <res name="Vegetation Density">Q150</res>
  </body>
  <body name="System EDIUR II" sectorname="" sectorcoords="309, 1, 5" systemname="EDIUR" systemcoords="-4.7, -0.8, 0.2" designation="" type="Planet" diameter="20800m" zone="Frigid" atmosphere="Corrosive" timestamp="8/11/2012 8:30:58 PM" outofrange="False">
    <res name="Bolite">Q181 1%, Q102 1%, Q9 1%</res>
    <res name="Coal">Q44 1%, Q168 1%, Q158 1%</res>
    <res name="Crystals">Q79 1%, Q73 1%, Q116 1%</res>
    <res name="Gems">Q172 1%, Q89 1%, Q96 1%</res>
    <res name="Ice">Q128 9%, Q165 8%, Q54 10%</res>
    <res name="Lumenite">Q121 1%, Q112 1%, Q169 1%</res>
    <res name="Minerals">Q164 1%, Q204 2%, Q125 1%</res>
    <res name="Natural Gas">Q148 1%, Q50 1%, Q45 1%</res>
    <res name="Oil">Q50 1%, Q118 1%, Q134 1%</res>
    <res name="Ore">Q132 1%, Q170 1%, Q227 1%</res>
    <res name="Polytaride">Q157 1%, Q190 1%, Q117 1%</res>
    <res name="Radioactives">Q79 1%, Q52 1%, Q73 1%</res>
    <res name="Stone">Q139 2%, Q144 2%, Q221 2%</res>
    <res name="Myrathane">Q161 70%</res>
    <res name="Air">Q122 72%</res>
    <res name="Cryozine">Q135 2%</res>
    <res name="Hydrogen">Q167 72%</res>
    <res name="Sunlight">Q46 10%</res>
    <res name="Animal Carcass">Q95, Q149, Q168</res>
    <res name="Beans">Q174, Q167, Q181</res>
    <res name="Cheese">Q214, Q97, Q67</res>
    <res name="Eggs">Q150, Q98, Q197</res>
    <res name="Fertilizer">Q77, Q99, Q121</res>
    <res name="Fruit">Q234, Q221, Q47</res>
    <res name="Grain">Q103, Q130, Q120</res>
    <res name="Grapes">Q149, Q199, Q27</res>
    <res name="Herbs">Q121, Q183, Q184</res>
    <res name="Hops">Q128, Q59, Q109</res>
    <res name="Log">Q200, Q131, Q175</res>
    <res name="Milk">Q103, Q83, Q195</res>
    <res name="Nuts">Q49, Q52, Q133</res>
    <res name="Plant Fiber">Q177, Q61, Q198</res>
    <res name="Spices">Q156, Q72, Q82</res>
    <res name="Vegetable">Q97, Q129, Q99</res>
    <res name="Vegetation Density">Q34, Q86, Q100</res>
  </body>
  <body name="System EDIUR IIa" sectorname="" sectorcoords="309, 1, 5" systemname="EDIUR" systemcoords="-4.7, -0.8, 0.2" designation="" type="Moon" diameter="3800m" zone="Frigid" atmosphere="No Atmosphere" timestamp="8/11/2012 8:30:58 PM" outofrange="False">
    <res name="Coal">Q143 1%</res>
    <res name="Crystals">Q167 1%</res>
    <res name="Eludium">Q224 11%</res>
    <res name="Gems">Q44 1%</res>
    <res name="Ice">Q141 1%</res>
    <res name="Lumenite">Q152 1%</res>
    <res name="Minerals">Q224 1%</res>
    <res name="Natural Gas">Q84 1%</res>
    <res name="Oil">Q68 1%</res>
    <res name="Ore">Q118 1%</res>
    <res name="Radioactives">Q40 1%</res>
    <res name="Stone">Q143 2%</res>
    <res name="Sunlight">Q81 10%</res>
    <res name="Animal Carcass">Q73</res>
    <res name="Beans">Q57</res>
    <res name="Cheese">Q111</res>
    <res name="Eggs">Q132</res>
    <res name="Fertilizer">Q115</res>
    <res name="Fruit">Q48</res>
    <res name="Grain">Q117</res>
    <res name="Grapes">Q216</res>
    <res name="Herbs">Q115</res>
    <res name="Hops">Q99</res>
    <res name="Log">Q140</res>
    <res name="Milk">Q112</res>
    <res name="Nuts">Q111</res>
    <res name="Plant Fiber">Q130</res>
    <res name="Spices">Q156</res>
    <res name="Vegetable">Q85</res>
    <res name="Vegetation Density">Q56</res>
  </body>
  <body name="System EDIUR IIb" sectorname="" sectorcoords="309, 1, 5" systemname="EDIUR" systemcoords="-4.7, -0.8, 0.2" designation="" type="Moon" diameter="1900m" zone="Frigid" atmosphere="No Atmosphere" timestamp="8/11/2012 8:30:58 PM" outofrange="False">
    <res name="Coal">Q99 1%</res>
    <res name="Crystals">Q188 1%</res>
    <res name="Eludium">Q132 42%</res>
    <res name="Gems">Q150 1%</res>
    <res name="Ice">Q43 1%</res>
    <res name="Lumenite">Q114 1%</res>
    <res name="Minerals">Q105 1%</res>
    <res name="Natural Gas">Q129 1%</res>
    <res name="Oil">Q80 1%</res>
    <res name="Ore">Q21 1%</res>
    <res name="Radioactives">Q125 1%</res>
    <res name="Stone">Q205 1%</res>
    <res name="Sunlight">Q192 10%</res>
    <res name="Animal Carcass">Q148</res>
    <res name="Beans">Q116</res>
    <res name="Cheese">Q98</res>
    <res name="Eggs">Q76</res>
    <res name="Fertilizer">Q160</res>
    <res name="Fruit">Q78</res>
    <res name="Grain">Q110</res>
    <res name="Grapes">Q119</res>
    <res name="Herbs">Q53</res>
    <res name="Hops">Q177</res>
    <res name="Log">Q106</res>
    <res name="Milk">Q107</res>
    <res name="Nuts">Q80</res>
    <res name="Plant Fiber">Q89</res>
    <res name="Spices">Q220</res>
    <res name="Vegetable">Q155</res>
    <res name="Vegetation Density">Q173</res>
  </body>
  <body name="System EDIUR III" sectorname="" sectorcoords="309, 1, 5" systemname="EDIUR" systemcoords="-4.7, -0.8, 0.2" designation="" type="Gas Giant" diameter="37900m" zone="Frigid" atmosphere="Corrosive" timestamp="8/11/2012 8:30:58 PM" outofrange="False">
    <res name="Air">Q41 98%</res>
    <res name="Borexino Precipitate">Q173 1%</res>
    <res name="Cryozine">Q140 3%</res>
    <res name="Hydrogen">Q120 98%</res>
    <res name="Sunlight">Q80 10%</res>
  </body>
  <body name="System EDIUR IIIa" sectorname="" sectorcoords="309, 1, 5" systemname="EDIUR" systemcoords="-4.7, -0.8, 0.2" designation="" type="Moon" diameter="3800m" zone="Frigid" atmosphere="No Atmosphere" timestamp="8/11/2012 8:30:58 PM" outofrange="False">
    <res name="Coal">Q42 1%</res>
    <res name="Crystals">Q59 1%</res>
    <res name="Eludium">Q171 46%</res>
    <res name="Gems">Q115 1%</res>
    <res name="Ice">Q81 1%</res>
    <res name="Lumenite">Q160 1%</res>
    <res name="Minerals">Q138 1%</res>
    <res name="Natural Gas">Q204 1%</res>
    <res name="Oil">Q62 1%</res>
    <res name="Ore">Q96 1%</res>
    <res name="Radioactives">Q204 1%</res>
    <res name="Stone">Q102 1%</res>
    <res name="Sunlight">Q243 10%</res>
    <res name="Animal Carcass">Q160</res>
    <res name="Beans">Q203</res>
    <res name="Cheese">Q113</res>
    <res name="Eggs">Q186</res>
    <res name="Fertilizer">Q243</res>
    <res name="Fruit">Q119</res>
    <res name="Grain">Q117</res>
    <res name="Grapes">Q190</res>
    <res name="Herbs">Q44</res>
    <res name="Hops">Q141</res>
    <res name="Log">Q92</res>
    <res name="Milk">Q143</res>
    <res name="Nuts">Q138</res>
    <res name="Plant Fiber">Q227</res>
    <res name="Spices">Q152</res>
    <res name="Vegetable">Q83</res>
    <res name="Vegetation Density">Q89</res>
  </body>
  <body name="System EDIUR IIIbr (1)" sectorname="" sectorcoords="309, 1, 5" systemname="EDIUR" systemcoords="-4.7, -0.8, 0.2" designation="" type="Ring" diameter="44100m" zone="Frigid" atmosphere="" timestamp="8/11/2012 8:30:58 PM" outofrange="False">
    <res name="Crystals">Q127 1%</res>
    <res name="Eludium">Q64 44%</res>
    <res name="Gems">Q53 1%</res>
    <res name="Ice">Q249 1%</res>
    <res name="Lumenite">Q146 1%</res>
    <res name="Minerals">Q112 1%</res>
    <res name="Ore">Q131 1%</res>
    <res name="Radioactives">Q205 1%</res>
    <res name="Stone">Q44 1%</res>
    <res name="Sunlight">Q39 10%</res>
  </body>
  <body name="System EDIUR IIIb" sectorname="" sectorcoords="309, 1, 5" systemname="EDIUR" systemcoords="-4.7, -0.8, 0.2" designation="" type="Moon" diameter="1900m" zone="Frigid" atmosphere="No Atmosphere" timestamp="8/11/2012 8:30:58 PM" outofrange="False">
    <res name="Coal">Q128 1%</res>
    <res name="Crystals">Q147 1%</res>
    <res name="Eludium">Q228 57%</res>
    <res name="Gems">Q159 1%</res>
    <res name="Ice">Q150 1%</res>
    <res name="Lumenite">Q108 1%</res>
    <res name="Minerals">Q120 1%</res>
    <res name="Natural Gas">Q116 1%</res>
    <res name="Oil">Q165 1%</res>
    <res name="Ore">Q162 1%</res>
    <res name="Radioactives">Q34 1%</res>
    <res name="Stone">Q106 1%</res>
    <res name="Sunlight">Q150 10%</res>
    <res name="Animal Carcass">Q139</res>
    <res name="Beans">Q86</res>
    <res name="Cheese">Q138</res>
    <res name="Eggs">Q167</res>
    <res name="Fertilizer">Q154</res>
    <res name="Fruit">Q61</res>
    <res name="Grain">Q130</res>
    <res name="Grapes">Q129</res>
    <res name="Herbs">Q166</res>
    <res name="Hops">Q111</res>
    <res name="Log">Q161</res>
    <res name="Milk">Q152</res>
    <res name="Nuts">Q71</res>
    <res name="Plant Fiber">Q179</res>
    <res name="Spices">Q152</res>
    <res name="Vegetable">Q197</res>
    <res name="Vegetation Density">Q111</res>
  </body>
  <body name="System EDIUR IIIc" sectorname="" sectorcoords="309, 1, 5" systemname="EDIUR" systemcoords="-4.7, -0.8, 0.2" designation="" type="Moon" diameter="3800m" zone="Frigid" atmosphere="No Atmosphere" timestamp="8/11/2012 8:30:58 PM" outofrange="False">
    <res name="Coal">Q126 1%</res>
    <res name="Crystals">Q80 1%</res>
    <res name="Eludium">Q79 34%</res>
    <res name="Gems">Q93 1%</res>
    <res name="Ice">Q109 1%</res>
    <res name="Lumenite">Q122 1%</res>
    <res name="Minerals">Q146 1%</res>
    <res name="Natural Gas">Q121 1%</res>
    <res name="Oil">Q74 1%</res>
    <res name="Ore">Q126 1%</res>
    <res name="Radioactives">Q33 1%</res>
    <res name="Stone">Q164 1%</res>
    <res name="Sunlight">Q97 10%</res>
    <res name="Animal Carcass">Q107</res>
    <res name="Beans">Q134</res>
    <res name="Cheese">Q229</res>
    <res name="Eggs">Q130</res>
    <res name="Fertilizer">Q161</res>
    <res name="Fruit">Q149</res>
    <res name="Grain">Q111</res>
    <res name="Grapes">Q93</res>
    <res name="Herbs">Q110</res>
    <res name="Hops">Q92</res>
    <res name="Log">Q185</res>
    <res name="Milk">Q138</res>
    <res name="Nuts">Q106</res>
    <res name="Plant Fiber">Q188</res>
    <res name="Spices">Q88</res>
    <res name="Vegetable">Q25</res>
    <res name="Vegetation Density">Q206</res>
  </body>
  <body name="System EDIUR IIId" sectorname="" sectorcoords="309, 1, 5" systemname="EDIUR" systemcoords="-4.7, -0.8, 0.2" designation="" type="Moon" diameter="3800m" zone="Frigid" atmosphere="No Atmosphere" timestamp="8/11/2012 8:30:58 PM" outofrange="False">
    <res name="Coal">Q213 1%</res>
    <res name="Crystals">Q39 1%</res>
    <res name="Eludium">Q136 52%</res>
    <res name="Gems">Q137 1%</res>
    <res name="Ice">Q51 1%</res>
    <res name="Minerals">Q129 1%</res>
    <res name="Natural Gas">Q32 1%</res>
    <res name="Oil">Q50 1%</res>
    <res name="Ore">Q193 1%</res>
    <res name="Radioactives">Q119 1%</res>
    <res name="Stone">Q167 1%</res>
    <res name="Sunlight">Q132 10%</res>
    <res name="Animal Carcass">Q213</res>
    <res name="Beans">Q145</res>
    <res name="Cheese">Q126</res>
    <res name="Eggs">Q113</res>
    <res name="Fertilizer">Q71</res>
    <res name="Fruit">Q91</res>
    <res name="Grain">Q124</res>
    <res name="Grapes">Q159</res>
    <res name="Herbs">Q105</res>
    <res name="Hops">Q62</res>
    <res name="Log">Q126</res>
    <res name="Milk">Q148</res>
    <res name="Nuts">Q168</res>
    <res name="Plant Fiber">Q139</res>
    <res name="Spices">Q89</res>
    <res name="Vegetable">Q140</res>
    <res name="Vegetation Density">Q228</res>
  </body>
  <body name="System EDIUR IV" sectorname="" sectorcoords="309, 1, 5" systemname="EDIUR" systemcoords="-4.7, -0.8, 0.2" designation="" type="Planet" diameter="13300m" zone="Frigid" atmosphere="Standard" timestamp="8/11/2012 8:30:58 PM" outofrange="False">
    <res name="Bolite">Q61 1%, Q183 1%, None</res>
    <res name="Coal">Q47 1%, Q223 1%, Q95 1%</res>
    <res name="Crystals">Q146 1%, Q113 1%, Q133 1%</res>
    <res name="Gems">Q136 1%, Q226 1%, Q150 1%</res>
    <res name="Ice">Q194 10%, Q140 9%, Q161 8%</res>
    <res name="Lumenite">Q185 1%, Q47 1%, Q72 1%</res>
    <res name="Minerals">Q44 1%, Q82 1%, Q197 1%</res>
    <res name="Natural Gas">Q44 1%, Q87 1%, Q85 1%</res>
    <res name="Oil">Q87 1%, Q30 1%, Q182 1%</res>
    <res name="Ore">Q113 1%, Q54 1%, Q192 1%</res>
    <res name="Polytaride">Q160 1%, Q113 1%, Q45 1%</res>
    <res name="Radioactives">Q133 1%, Q38 1%, Q183 2%</res>
    <res name="Stone">Q81 2%, Q127 2%, Q115 2%</res>
    <res name="Myrathane">Q154 72%</res>
    <res name="Air">Q159 43%</res>
    <res name="Hydrogen">Q72 43%</res>
    <res name="Sunlight">Q99 10%</res>
    <res name="Animal Carcass">Q127, Q75, Q170</res>
    <res name="Beans">Q126, Q141, Q150</res>
    <res name="Cheese">Q123, Q189, Q42</res>
    <res name="Eggs">Q59, Q136, Q185</res>
    <res name="Fertilizer">Q199, Q97, Q134</res>
    <res name="Fruit">Q147, Q176, Q126</res>
    <res name="Grain">Q122, Q73, Q115</res>
    <res name="Grapes">Q185, Q125, Q162</res>
    <res name="Herbs">Q176, Q50, Q184</res>
    <res name="Hops">Q148, Q96, Q233</res>
    <res name="Log">Q47, Q177, Q81</res>
    <res name="Milk">Q118, Q194, Q110</res>
    <res name="Nuts">Q142, Q167, Q106</res>
    <res name="Plant Fiber">Q42, Q36, Q94</res>
    <res name="Spices">Q93, Q71, Q130</res>
    <res name="Vegetable">Q143, Q132, Q118</res>
    <res name="Vegetation Density">Q195, Q53, Q36</res>
  </body>
  <body name="System EDIUR IVa" sectorname="" sectorcoords="309, 1, 5" systemname="EDIUR" systemcoords="-4.7, -0.8, 0.2" designation="" type="Moon" diameter="1900m" zone="Frigid" atmosphere="No Atmosphere" timestamp="8/11/2012 8:30:58 PM" outofrange="False">
    <res name="Coal">Q188 1%</res>
    <res name="Crystals">Q215 1%</res>
    <res name="Eludium">Q81 56%</res>
    <res name="Gems">Q133 1%</res>
    <res name="Ice">Q154 1%</res>
    <res name="Lumenite">Q175 1%</res>
    <res name="Minerals">Q190 1%</res>
    <res name="Natural Gas">Q163 1%</res>
    <res name="Oil">Q146 1%</res>
    <res name="Ore">Q251 1%</res>
    <res name="Radioactives">Q211 1%</res>
    <res name="Stone">Q151 1%</res>
    <res name="Sunlight">Q151 10%</res>
    <res name="Animal Carcass">Q158</res>
    <res name="Beans">Q207</res>
    <res name="Cheese">Q34</res>
    <res name="Eggs">Q95</res>
    <res name="Fertilizer">Q64</res>
    <res name="Fruit">Q188</res>
    <res name="Grain">Q142</res>
    <res name="Grapes">Q93</res>
    <res name="Herbs">Q103</res>
    <res name="Hops">Q167</res>
    <res name="Log">Q151</res>
    <res name="Milk">Q131</res>
    <res name="Nuts">Q234</res>
    <res name="Plant Fiber">Q33</res>
    <res name="Spices">Q157</res>
    <res name="Vegetable">Q188</res>
    <res name="Vegetation Density">Q101</res>
  </body>
  <body name="System EDIUR IVb" sectorname="" sectorcoords="309, 1, 5" systemname="EDIUR" systemcoords="-4.7, -0.8, 0.2" designation="" type="Moon" diameter="3800m" zone="Frigid" atmosphere="No Atmosphere" timestamp="8/11/2012 8:30:58 PM" outofrange="False">
    <res name="Coal">Q144 1%</res>
    <res name="Crystals">Q106 1%</res>
    <res name="Eludium">Q117 50%</res>
    <res name="Gems">Q110 1%</res>
    <res name="Ice">Q54 1%</res>
    <res name="Lumenite">Q137 1%</res>
    <res name="Minerals">Q71 1%</res>
    <res name="Natural Gas">Q80 1%</res>
    <res name="Oil">Q158 1%</res>
    <res name="Ore">Q26 1%</res>
    <res name="Radioactives">Q40 1%</res>
    <res name="Stone">Q86 1%</res>
    <res name="Sunlight">Q134 10%</res>
    <res name="Animal Carcass">Q104</res>
    <res name="Beans">Q138</res>
    <res name="Cheese">Q22</res>
    <res name="Eggs">Q168</res>
    <res name="Fertilizer">Q109</res>
    <res name="Fruit">Q88</res>
    <res name="Grain">Q136</res>
    <res name="Grapes">Q124</res>
    <res name="Herbs">Q170</res>
    <res name="Hops">Q118</res>
    <res name="Log">Q116</res>
    <res name="Milk">Q127</res>
    <res name="Nuts">Q203</res>
    <res name="Plant Fiber">Q121</res>
    <res name="Spices">Q93</res>
    <res name="Vegetable">Q131</res>
    <res name="Vegetation Density">Q217</res>
  </body>
  <body name="System EDIUR IVcr (1)" sectorname="" sectorcoords="309, 1, 5" systemname="EDIUR" systemcoords="-4.7, -0.8, 0.2" designation="" type="Ring" diameter="70600m" zone="Frigid" atmosphere="" timestamp="8/11/2012 8:30:58 PM" outofrange="False">
    <res name="Crystals">Q127 1%</res>
    <res name="Eludium">Q153 40%</res>
    <res name="Gems">Q88 1%</res>
    <res name="Ice">Q83 1%</res>
    <res name="Lumenite">Q228 1%</res>
    <res name="Minerals">Q207 1%</res>
    <res name="Ore">Q56 1%</res>
    <res name="Radioactives">Q126 1%</res>
    <res name="Stone">Q147 1%</res>
    <res name="Sunlight">Q116 10%</res>
  </body>
  <body name="System EDIUR V" sectorname="" sectorcoords="309, 1, 5" systemname="EDIUR" systemcoords="-4.7, -0.8, 0.2" designation="" type="Planet" diameter="13300m" zone="Frigid" atmosphere="Exotic" timestamp="8/11/2012 8:30:58 PM" outofrange="False">
    <res name="Bolite">Q227 1%, Q152 1%, None</res>
    <res name="Coal">Q165 1%, Q207 1%, Q29 1%</res>
    <res name="Crystals">Q107 1%, Q184 1%, Q41 1%</res>
    <res name="Gems">Q39 1%, Q173 1%, Q98 1%</res>
    <res name="Ice">Q203 16%, Q112 17%, Q200 43%</res>
    <res name="Lumenite">Q82 1%, Q112 1%, Q189 1%</res>
    <res name="Minerals">Q212 1%, Q48 1%, Q49 1%</res>
    <res name="Natural Gas">Q166 1%, Q134 1%, Q161 1%</res>
    <res name="Oil">Q45 1%, Q103 1%, Q129 1%</res>
    <res name="Ore">Q47 1%, Q75 1%, Q133 1%</res>
    <res name="Polytaride">None, None, Q110 1%</res>
    <res name="Radioactives">Q168 1%, Q81 1%, Q106 1%</res>
    <res name="Stone">Q110 1%, Q99 1%, Q161 1%</res>
    <res name="Myrathane">Q106 83%</res>
    <res name="Air">Q116 61%</res>
    <res name="Cryozine">Q203 1%</res>
    <res name="Hydrogen">Q58 61%</res>
    <res name="Sunlight">Q57 10%</res>
    <res name="Animal Carcass">Q117, Q30, Q202</res>
    <res name="Beans">Q97, Q116, Q111</res>
    <res name="Cheese">Q164, Q49, Q58</res>
    <res name="Eggs">Q149, Q10, Q83</res>
    <res name="Fertilizer">Q192, Q63, Q192</res>
    <res name="Fruit">Q131, Q174, Q64</res>
    <res name="Grain">Q143, Q96, Q108</res>
    <res name="Grapes">Q67, Q201, Q80</res>
    <res name="Herbs">Q161, Q165, Q231</res>
    <res name="Hops">Q209, Q135, Q175</res>
    <res name="Log">Q101, Q173, Q100</res>
    <res name="Milk">Q35, Q73, Q122</res>
    <res name="Nuts">Q132, Q195, Q46</res>
    <res name="Plant Fiber">Q131, Q222, Q127</res>
    <res name="Spices">Q154, Q36, Q159</res>
    <res name="Vegetable">Q185, Q112, Q136</res>
    <res name="Vegetation Density">Q133, Q155, Q101</res>
  </body>
  <body name="System EDIUR VI" sectorname="" sectorcoords="309, 1, 5" systemname="EDIUR" systemcoords="-4.7, -0.8, 0.2" designation="" type="Gas Giant" diameter="64400m" zone="Frigid" atmosphere="Exotic" timestamp="8/11/2012 8:30:58 PM" outofrange="False">
    <res name="Air">Q137 95%</res>
    <res name="Borexino Precipitate">Q173 2%</res>
    <res name="Cryozine">Q169 2%</res>
    <res name="Hydrogen">Q69 95%</res>
    <res name="Sunlight">Q145 10%</res>
  </body>
  <body name="System EDIUR VIa" sectorname="" sectorcoords="309, 1, 5" systemname="EDIUR" systemcoords="-4.7, -0.8, 0.2" designation="" type="Moon" diameter="3800m" zone="Frigid" atmosphere="No Atmosphere" timestamp="8/11/2012 8:30:58 PM" outofrange="False">
    <res name="Coal">Q8 1%</res>
    <res name="Crystals">Q93 1%</res>
    <res name="Eludium">Q162 55%</res>
    <res name="Gems">Q102 1%</res>
    <res name="Ice">Q146 1%</res>
    <res name="Lumenite">Q194 1%</res>
    <res name="Minerals">Q44 1%</res>
    <res name="Natural Gas">Q100 1%</res>
    <res name="Oil">Q52 1%</res>
    <res name="Ore">Q140 1%</res>
    <res name="Radioactives">Q164 1%</res>
    <res name="Stone">Q188 1%</res>
    <res name="Sunlight">Q179 10%</res>
    <res name="Animal Carcass">Q105</res>
    <res name="Beans">Q200</res>
    <res name="Cheese">Q125</res>
    <res name="Eggs">Q149</res>
    <res name="Fertilizer">Q135</res>
    <res name="Fruit">Q183</res>
    <res name="Grain">Q187</res>
    <res name="Grapes">Q108</res>
    <res name="Herbs">Q76</res>
    <res name="Hops">Q169</res>
    <res name="Log">Q215</res>
    <res name="Milk">Q196</res>
    <res name="Nuts">Q219</res>
    <res name="Plant Fiber">Q26</res>
    <res name="Spices">Q91</res>
    <res name="Vegetable">Q78</res>
    <res name="Vegetation Density">Q83</res>
  </body>
  <body name="System EDIUR VIb" sectorname="" sectorcoords="309, 1, 5" systemname="EDIUR" systemcoords="-4.7, -0.8, 0.2" designation="" type="Large Moon" diameter="15200m" zone="Frigid" atmosphere="Tainted" timestamp="8/11/2012 8:30:58 PM" outofrange="False">
    <res name="Bolite">Q115 1%, Q58 1%, Q58 1%</res>
    <res name="Coal">Q40 1%, Q190 1%, Q29 1%</res>
    <res name="Crystals">Q113 1%, Q9 1%, Q201 1%</res>
    <res name="Gems">Q96 1%, Q64 1%, Q79 1%</res>
    <res name="Ice">Q79 24%, Q190 24%, Q155 15%</res>
    <res name="Lumenite">None, Q112 1%, Q126 1%</res>
    <res name="Minerals">Q228 1%, Q60 1%, Q63 1%</res>
    <res name="Natural Gas">Q85 1%, Q208 1%, Q111 1%</res>
    <res name="Oil">Q120 1%, Q55 1%, Q222 1%</res>
    <res name="Ore">Q137 1%, Q98 1%, Q192 1%</res>
    <res name="Polytaride">Q146 1%, Q184 1%, None</res>
    <res name="Radioactives">Q20 1%, Q178 1%, Q201 1%</res>
    <res name="Stone">Q122 1%, Q64 1%, Q78 1%</res>
    <res name="Myrathane">Q93 79%</res>
    <res name="Air">Q64 98%</res>
    <res name="Cryozine">Q137 1%</res>
    <res name="Hydrogen">Q122 98%</res>
    <res name="Sunlight">Q162 10%</res>
    <res name="Animal Carcass">Q180, Q136, Q77</res>
    <res name="Beans">Q130, Q192, Q50</res>
    <res name="Cheese">Q240, Q106, Q135</res>
    <res name="Eggs">Q95, Q84, Q58</res>
    <res name="Fertilizer">Q51, Q189, Q89</res>
    <res name="Fruit">Q84, Q84, Q93</res>
    <res name="Grain">Q53, Q110, Q96</res>
    <res name="Grapes">Q139, Q54, Q94</res>
    <res name="Herbs">Q143, Q155, Q101</res>
    <res name="Hops">Q119, Q84, Q165</res>
    <res name="Log">Q180, Q9, Q168</res>
    <res name="Milk">Q191, Q40, Q208</res>
    <res name="Nuts">Q188, Q43, Q120</res>
    <res name="Plant Fiber">Q114, Q43, Q48</res>
    <res name="Spices">Q26, Q33, Q126</res>
    <res name="Vegetable">Q148, Q119, Q175</res>
    <res name="Vegetation Density">Q200, Q88, Q100</res>
  </body>
  <body name="System EDIUR VII" sectorname="" sectorcoords="309, 1, 5" systemname="EDIUR" systemcoords="-4.7, -0.8, 0.2" designation="" type="Planet" diameter="7600m" zone="Frigid" atmosphere="Corrosive" timestamp="8/11/2012 8:30:58 PM" outofrange="False">
    <res name="Bolite">Q40 1%, Q99 1%, None</res>
    <res name="Coal">Q101 1%, Q146 1%, Q86 1%</res>
    <res name="Crystals">Q86 1%, Q108 1%, Q124 1%</res>
    <res name="Eludium">Q120 56%, Q66 62%, Q214 62%</res>
    <res name="Gems">Q98 1%, Q201 1%, Q114 1%</res>
    <res name="Ice">Q192 1%, Q176 1%, Q142 1%</res>
    <res name="Lumenite">Q94 1%, Q112 1%, Q121 1%</res>
    <res name="Minerals">Q96 1%, Q198 1%, Q185 1%</res>
    <res name="Natural Gas">Q59 1%, Q144 1%, Q48 1%</res>
    <res name="Oil">Q174 1%, Q37 1%, Q128 1%</res>
    <res name="Ore">Q69 1%, Q88 1%, Q168 1%</res>
    <res name="Polytaride">None, None, Q91 1%</res>
    <res name="Radioactives">Q163 1%, Q86 1%, Q115 1%</res>
    <res name="Stone">Q48 1%, Q197 1%, Q233 1%</res>
    <res name="Myrathane">Q58 1%</res>
    <res name="Air">Q172 5%</res>
    <res name="Hydrogen">Q111 5%</res>
    <res name="Sunlight">Q203 10%</res>
    <res name="Animal Carcass">Q171, Q80, Q164</res>
    <res name="Beans">Q166, Q128, Q90</res>
    <res name="Cheese">Q176, Q235, Q69</res>
    <res name="Eggs">Q204, Q148, Q137</res>
    <res name="Fertilizer">Q148, Q110, Q120</res>
    <res name="Fruit">Q229, Q162, Q167</res>
    <res name="Grain">Q149, Q91, Q145</res>
    <res name="Grapes">Q164, Q120, Q89</res>
    <res name="Herbs">Q93, Q148, Q80</res>
    <res name="Hops">Q131, Q149, Q89</res>
    <res name="Log">Q136, Q176, Q49</res>
    <res name="Milk">Q167, Q92, Q35</res>
    <res name="Nuts">Q35, Q120, Q142</res>
    <res name="Plant Fiber">Q170, Q159, Q191</res>
    <res name="Spices">Q89, Q114, Q69</res>
    <res name="Vegetable">Q115, Q189, Q117</res>
    <res name="Vegetation Density">Q16, Q192, Q178</res>
  </body>
  <body name="System EDIUR VIIa" sectorname="" sectorcoords="309, 1, 5" systemname="EDIUR" systemcoords="-4.7, -0.8, 0.2" designation="" type="Moon" diameter="3800m" zone="Frigid" atmosphere="No Atmosphere" timestamp="8/11/2012 8:30:58 PM" outofrange="False">
    <res name="Coal">Q133 1%</res>
    <res name="Crystals">Q154 1%</res>
    <res name="Eludium">Q142 26%</res>
    <res name="Gems">Q164 1%</res>
    <res name="Ice">Q104 1%</res>
    <res name="Lumenite">Q80 1%</res>
    <res name="Minerals">Q198 1%</res>
    <res name="Natural Gas">Q105 1%</res>
    <res name="Oil">Q90 1%</res>
    <res name="Ore">Q105 1%</res>
    <res name="Radioactives">Q163 1%</res>
    <res name="Stone">Q118 1%</res>
    <res name="Sunlight">Q127 10%</res>
    <res name="Animal Carcass">Q201</res>
    <res name="Beans">Q119</res>
    <res name="Cheese">Q215</res>
    <res name="Eggs">Q113</res>
    <res name="Fertilizer">Q13</res>
    <res name="Fruit">Q143</res>
    <res name="Grain">Q40</res>
    <res name="Grapes">Q72</res>
    <res name="Herbs">Q149</res>
    <res name="Hops">Q150</res>
    <res name="Log">Q112</res>
    <res name="Milk">Q182</res>
    <res name="Nuts">Q126</res>
    <res name="Plant Fiber">Q35</res>
    <res name="Spices">Q154</res>
    <res name="Vegetable">Q160</res>
    <res name="Vegetation Density">Q178</res>
  </body>
  <body name="System EDIUR VIIb" sectorname="" sectorcoords="309, 1, 5" systemname="EDIUR" systemcoords="-4.7, -0.8, 0.2" designation="" type="Moon" diameter="3800m" zone="Frigid" atmosphere="No Atmosphere" timestamp="8/11/2012 8:30:58 PM" outofrange="False">
    <res name="Coal">Q174 1%</res>
    <res name="Crystals">Q66 1%</res>
    <res name="Eludium">Q85 41%</res>
    <res name="Gems">Q119 1%</res>
    <res name="Ice">Q163 1%</res>
    <res name="Lumenite">Q132 1%</res>
    <res name="Minerals">Q215 1%</res>
    <res name="Natural Gas">Q194 1%</res>
    <res name="Oil">Q115 1%</res>
    <res name="Ore">Q166 1%</res>
    <res name="Radioactives">Q77 1%</res>
    <res name="Stone">Q114 1%</res>
    <res name="Sunlight">Q92 10%</res>
    <res name="Animal Carcass">Q223</res>
    <res name="Beans">Q108</res>
    <res name="Cheese">Q190</res>
    <res name="Eggs">Q131</res>
    <res name="Fertilizer">Q230</res>
    <res name="Fruit">Q73</res>
    <res name="Grain">Q156</res>
    <res name="Grapes">Q134</res>
    <res name="Herbs">Q27</res>
    <res name="Hops">Q179</res>
    <res name="Log">Q170</res>
    <res name="Milk">Q172</res>
    <res name="Nuts">Q66</res>
    <res name="Plant Fiber">Q83</res>
    <res name="Spices">Q154</res>
    <res name="Vegetable">Q173</res>
    <res name="Vegetation Density">Q156</res>
  </body>
  <body name="System EDIUR VIIc" sectorname="" sectorcoords="309, 1, 5" systemname="EDIUR" systemcoords="-4.7, -0.8, 0.2" designation="" type="Moon" diameter="3800m" zone="Frigid" atmosphere="No Atmosphere" timestamp="8/11/2012 8:30:58 PM" outofrange="False">
    <res name="Coal">Q89 1%</res>
    <res name="Crystals">Q46 1%</res>
    <res name="Eludium">Q177 50%</res>
    <res name="Gems">Q141 1%</res>
    <res name="Ice">Q133 1%</res>
    <res name="Lumenite">Q170 1%</res>
    <res name="Minerals">Q79 1%</res>
    <res name="Natural Gas">Q21 1%</res>
    <res name="Oil">Q103 1%</res>
    <res name="Ore">Q135 1%</res>
    <res name="Radioactives">Q120 1%</res>
    <res name="Stone">Q180 1%</res>
    <res name="Sunlight">Q110 10%</res>
    <res name="Animal Carcass">Q148</res>
    <res name="Beans">Q178</res>
    <res name="Cheese">Q202</res>
    <res name="Eggs">Q58</res>
    <res name="Fertilizer">Q186</res>
    <res name="Fruit">Q43</res>
    <res name="Grain">Q33</res>
    <res name="Grapes">Q103</res>
    <res name="Herbs">Q216</res>
    <res name="Hops">Q100</res>
    <res name="Log">Q205</res>
    <res name="Milk">Q49</res>
    <res name="Nuts">Q96</res>
    <res name="Plant Fiber">Q123</res>
    <res name="Spices">Q89</res>
    <res name="Vegetable">Q102</res>
    <res name="Vegetation Density">Q38</res>
  </body>
  <body name="System EDIUR VIII" sectorname="" sectorcoords="309, 1, 5" systemname="EDIUR" systemcoords="-4.7, -0.8, 0.2" designation="" type="Planet" diameter="15200m" zone="Frigid" atmosphere="Standard" timestamp="8/11/2012 8:30:58 PM" outofrange="False">
    <res name="Bolite">Q164 1%, Q197 1%, None</res>
    <res name="Coal">Q169 1%, Q56 1%, Q158 1%</res>
    <res name="Crystals">Q73 2%, Q121 1%, Q84 1%</res>
    <res name="Gems">Q243 1%, Q199 1%, Q115 1%</res>
    <res name="Ice">Q124 7%, Q87 6%, Q99 23%</res>
    <res name="Lumenite">Q123 1%, Q112 1%, Q104 1%</res>
    <res name="Minerals">Q148 1%, Q192 1%, Q110 1%</res>
    <res name="Natural Gas">Q229 1%, Q104 1%, Q95 1%</res>
    <res name="Oil">Q102 1%, Q38 1%, Q41 1%</res>
    <res name="Ore">Q168 1%, Q20 2%, Q40 1%</res>
    <res name="Polytaride">Q149 1%, Q89 1%, Q132 1%</res>
    <res name="Radioactives">Q99 1%, Q83 1%, Q105 1%</res>
    <res name="Stone">Q126 2%, Q52 2%, Q178 1%</res>
    <res name="Myrathane">Q46 67%</res>
    <res name="Air">Q46 93%</res>
    <res name="Hydrogen">Q101 93%</res>
    <res name="Sunlight">Q69 10%</res>
    <res name="Animal Carcass">Q159, Q43, Q164</res>
    <res name="Beans">Q142, Q90, Q114</res>
    <res name="Cheese">Q137, Q167, Q246</res>
    <res name="Eggs">Q76, Q152, Q221</res>
    <res name="Fertilizer">Q89, Q102, Q97</res>
    <res name="Fruit">Q153, Q54, Q18</res>
    <res name="Grain">Q194, Q115, Q5</res>
    <res name="Grapes">Q78, Q90, Q142</res>
    <res name="Herbs">Q138, Q194, Q58</res>
    <res name="Hops">Q90, Q109, Q120</res>
    <res name="Log">Q121, Q39, Q107</res>
    <res name="Milk">Q73, Q115, Q109</res>
    <res name="Nuts">Q121, Q205, Q59</res>
    <res name="Plant Fiber">Q194, Q112, Q149</res>
    <res name="Spices">Q26, Q75, Q115</res>
    <res name="Vegetable">Q8, Q122, Q60</res>
    <res name="Vegetation Density">Q223, Q152, Q228</res>
  </body>
  <body name="System EDIUR VIIIa" sectorname="" sectorcoords="309, 1, 5" systemname="EDIUR" systemcoords="-4.7, -0.8, 0.2" designation="" type="Moon" diameter="3800m" zone="Frigid" atmosphere="No Atmosphere" timestamp="8/11/2012 8:30:58 PM" outofrange="False">
    <res name="Coal">Q181 1%</res>
    <res name="Crystals">Q140 1%</res>
    <res name="Eludium">Q147 33%</res>
    <res name="Gems">Q190 1%</res>
    <res name="Ice">Q158 1%</res>
    <res name="Lumenite">Q90 1%</res>
    <res name="Minerals">Q138 1%</res>
    <res name="Natural Gas">Q50 1%</res>
    <res name="Oil">Q130 1%</res>
    <res name="Ore">Q144 1%</res>
    <res name="Radioactives">Q81 1%</res>
    <res name="Stone">Q68 1%</res>
    <res name="Sunlight">Q122 10%</res>
    <res name="Animal Carcass">Q191</res>
    <res name="Beans">Q94</res>
    <res name="Cheese">Q176</res>
    <res name="Eggs">Q113</res>
    <res name="Fertilizer">Q84</res>
    <res name="Fruit">Q66</res>
    <res name="Grain">Q213</res>
    <res name="Grapes">Q241</res>
    <res name="Herbs">Q65</res>
    <res name="Hops">Q109</res>
    <res name="Log">Q96</res>
    <res name="Milk">Q88</res>
    <res name="Nuts">Q86</res>
    <res name="Plant Fiber">Q186</res>
    <res name="Spices">Q219</res>
    <res name="Vegetable">Q181</res>
    <res name="Vegetation Density">Q128</res>
  </body>
  <body name="System EDIUR VIIIb" sectorname="" sectorcoords="309, 1, 5" systemname="EDIUR" systemcoords="-4.7, -0.8, 0.2" designation="" type="Moon" diameter="1900m" zone="Frigid" atmosphere="No Atmosphere" timestamp="8/11/2012 8:30:58 PM" outofrange="False">
    <res name="Coal">Q222 1%</res>
    <res name="Crystals">Q180 1%</res>
    <res name="Eludium">Q90 47%</res>
    <res name="Gems">Q146 1%</res>
    <res name="Ice">Q87 1%</res>
    <res name="Lumenite">Q142 1%</res>
    <res name="Minerals">Q155 1%</res>
    <res name="Natural Gas">Q140 1%</res>
    <res name="Oil">Q155 1%</res>
    <res name="Ore">Q78 1%</res>
    <res name="Radioactives">Q123 1%</res>
    <res name="Stone">Q65 1%</res>
    <res name="Sunlight">Q86 10%</res>
    <res name="Animal Carcass">Q212</res>
    <res name="Beans">Q210</res>
    <res name="Cheese">Q150</res>
    <res name="Eggs">Q131</res>
    <res name="Fertilizer">Q173</res>
    <res name="Fruit">Q124</res>
    <res name="Grain">Q200</res>
    <res name="Grapes">Q175</res>
    <res name="Herbs">Q198</res>
    <res name="Hops">Q139</res>
    <res name="Log">Q28</res>
    <res name="Milk">Q206</res>
    <res name="Nuts">Q152</res>
    <res name="Plant Fiber">Q235</res>
    <res name="Spices">Q91</res>
    <res name="Vegetable">Q193</res>
    <res name="Vegetation Density">Q105</res>
  </body>
  <body name="System EDIUR VIIIc" sectorname="" sectorcoords="309, 1, 5" systemname="EDIUR" systemcoords="-4.7, -0.8, 0.2" designation="" type="Moon" diameter="3800m" zone="Frigid" atmosphere="No Atmosphere" timestamp="8/11/2012 8:30:58 PM" outofrange="False">
    <res name="Coal">Q138 1%</res>
    <res name="Crystals">Q161 1%</res>
    <res name="Eludium">Q55 53%</res>
    <res name="Gems">Q168 1%</res>
    <res name="Ice">Q186 1%</res>
    <res name="Lumenite">Q52 1%</res>
    <res name="Minerals">Q147 1%</res>
    <res name="Natural Gas">Q94 1%</res>
    <res name="Oil">Q142 1%</res>
    <res name="Ore">Q47 1%</res>
    <res name="Radioactives">Q166 1%</res>
    <res name="Stone">Q131 1%</res>
    <res name="Sunlight">Q232 10%</res>
    <res name="Animal Carcass">Q137</res>
    <res name="Beans">Q24</res>
    <res name="Cheese">Q163</res>
    <res name="Eggs">Q187</res>
    <res name="Fertilizer">Q128</res>
    <res name="Fruit">Q95</res>
    <res name="Grain">Q206</res>
    <res name="Grapes">Q144</res>
    <res name="Herbs">Q132</res>
    <res name="Hops">Q60</res>
    <res name="Log">Q189</res>
    <res name="Milk">Q83</res>
    <res name="Nuts">Q182</res>
    <res name="Plant Fiber">Q146</res>
    <res name="Spices">Q155</res>
    <res name="Vegetable">Q123</res>
    <res name="Vegetation Density">Q245</res>
  </body>
</database>