<?xml version="1.0" encoding="utf-8" standalone="yes"?>
<database application="Hazeron Scouter" version="0.3.3.4">
  <body name="M0 V Main Sequence Alpha" sectorname="" sectorcoords="310, 1, 4" systemname="FWCTR" systemcoords="-2.5, -0.6, 3.8" designation="Alpha" type="Star" diameter="0.095au" zone="" atmosphere="" timestamp="8/11/2012 6:26:59 PM" outofrange="False">
    <res name="Type M Preons">Q141 5%</res>
  </body>
  <body name="DA Blue Dwarf Beta" sectorname="" sectorcoords="310, 1, 4" systemname="FWCTR" systemcoords="-2.5, -0.6, 3.8" designation="Alpha" type="Star" diameter="0.085au" zone="" atmosphere="" timestamp="8/11/2012 6:26:59 PM" outofrange="False">
    <res name="Type A Preons">Q134 5%</res>
  </body>
  <body name="System FWCTR Beta I" sectorname="" sectorcoords="310, 1, 4" systemname="FWCTR" systemcoords="-2.5, -0.6, 3.8" designation="Beta" type="Planet" diameter="11400m" zone="Outer" atmosphere="Standard" timestamp="8/11/2012 6:26:59 PM" outofrange="False">
    <res name="Coal">Q74 1%, Q130 1%, Q131 1%</res>
    <res name="Crystals">Q44 1%, Q134 1%, Q126 1%</res>
    <res name="Gems">Q159 1%, Q151 2%, Q116 1%</res>
    <res name="Ice">Q110 2%, Q115 4%, Q34 4%</res>
    <res name="Lumenite">Q123 1%, Q102 1%, Q146 1%</res>
    <res name="Minerals">Q119 1%, Q151 1%, Q159 1%</res>
    <res name="Natural Gas">Q63 1%, Q137 1%, Q105 1%</res>
    <res name="Oil">Q172 1%, Q82 1%, Q114 1%</res>
    <res name="Ore">Q171 1%, Q118 1%, Q123 1%</res>
    <res name="Radioactives">Q150 1%, Q185 1%, Q90 2%</res>
    <res name="Stone">Q60 2%, Q62 2%, Q158 2%</res>
    <res name="Water in the Environment">Q62 25%</res>
    <res name="Air">Q74 82%</res>
    <res name="Hydrogen">Q111 82%</res>
    <res name="Sunlight">Q154 30%</res>
    <res name="Animal Carcass">Q71, Q46, Q135</res>
    <res name="Beans">Q25, Q158, Q108</res>
    <res name="Cheese">Q149, Q91, Q137</res>
    <res name="Eggs">Q85, Q24, Q183</res>
    <res name="Fertilizer">Q116, Q46, Q145</res>
    <res name="Fish">Q67, Q27, Q156</res>
    <res name="Fruit">Q99, Q128, Q135</res>
    <res name="Grain">Q32, Q174, Q209</res>
    <res name="Grapes">Q43, Q126, Q79</res>
    <res name="Herbs">Q195, Q145, Q193</res>
    <res name="Hops">Q136, Q142, Q63</res>
    <res name="Log">Q207, Q145, Q204</res>
    <res name="Milk">Q99, Q90, Q122</res>
    <res name="Nuts">Q159, Q113, Q237</res>
    <res name="Plant Fiber">Q118, Q77, Q91</res>
    <res name="Spices">Q125, Q155, Q121</res>
    <res name="Vegetable">Q190, Q118, Q64</res>
    <res name="Vegetation Density">Q90, Q185, Q164</res>
  </body>
  <body name="System FWCTR Beta Ia" sectorname="" sectorcoords="310, 1, 4" systemname="FWCTR" systemcoords="-2.5, -0.6, 3.8" designation="Beta" type="Moon" diameter="3800m" zone="Outer" atmosphere="No Atmosphere" timestamp="8/11/2012 6:26:59 PM" outofrange="False">
    <res name="Coal">Q55 1%</res>
    <res name="Crystals">Q201 1%</res>
    <res name="Eludium">Q37 53%</res>
    <res name="Gems">Q110 1%</res>
    <res name="Ice">Q51 1%</res>
    <res name="Lumenite">Q144 1%</res>
    <res name="Minerals">Q145 1%</res>
    <res name="Natural Gas">Q87 1%</res>
    <res name="Oil">Q104 1%</res>
    <res name="Ore">Q97 1%</res>
    <res name="Radioactives">Q99 1%</res>
    <res name="Stone">Q74 1%</res>
    <res name="Sunlight">Q189 30%</res>
    <res name="Animal Carcass">Q137</res>
    <res name="Beans">Q168</res>
    <res name="Cheese">Q139</res>
    <res name="Eggs">Q155</res>
    <res name="Fertilizer">Q100</res>
    <res name="Fruit">Q60</res>
    <res name="Grain">Q22</res>
    <res name="Grapes">Q97</res>
    <res name="Herbs">Q154</res>
    <res name="Hops">Q20</res>
    <res name="Log">Q122</res>
    <res name="Milk">Q25</res>
    <res name="Nuts">Q161</res>
    <res name="Plant Fiber">Q139</res>
    <res name="Spices">Q195</res>
    <res name="Vegetable">Q61</res>
    <res name="Vegetation Density">Q113</res>
  </body>
  <body name="System FWCTR Beta Ib" sectorname="" sectorcoords="310, 1, 4" systemname="FWCTR" systemcoords="-2.5, -0.6, 3.8" designation="Beta" type="Moon" diameter="3800m" zone="Outer" atmosphere="No Atmosphere" timestamp="8/11/2012 6:26:59 PM" outofrange="False">
    <res name="Coal">Q182 1%</res>
    <res name="Crystals">Q94 1%</res>
    <res name="Eludium">Q201 47%</res>
    <res name="Gems">Q216 1%</res>
    <res name="Ice">Q208 1%</res>
    <res name="Lumenite">Q234 1%</res>
    <res name="Minerals">Q153 1%</res>
    <res name="Natural Gas">Q207 1%</res>
    <res name="Oil">Q176 1%</res>
    <res name="Ore">Q128 1%</res>
    <res name="Radioactives">Q56 1%</res>
    <res name="Stone">Q136 1%</res>
    <res name="Sunlight">Q171 30%</res>
    <res name="Animal Carcass">Q84</res>
    <res name="Beans">Q99</res>
    <res name="Cheese">Q127</res>
    <res name="Eggs">Q228</res>
    <res name="Fertilizer">Q145</res>
    <res name="Fruit">Q88</res>
    <res name="Grain">Q15</res>
    <res name="Grapes">Q128</res>
    <res name="Herbs">Q221</res>
    <res name="Hops">Q99</res>
    <res name="Log">Q87</res>
    <res name="Milk">Q148</res>
    <res name="Nuts">Q131</res>
    <res name="Plant Fiber">Q99</res>
    <res name="Spices">Q131</res>
    <res name="Vegetable">Q132</res>
    <res name="Vegetation Density">Q230</res>
  </body>
  <body name="System FWCTR Beta Ic" sectorname="" sectorcoords="310, 1, 4" systemname="FWCTR" systemcoords="-2.5, -0.6, 3.8" designation="Beta" type="Moon" diameter="3800m" zone="Outer" atmosphere="No Atmosphere" timestamp="8/11/2012 6:26:59 PM" outofrange="False">
    <res name="Coal">Q56 1%</res>
    <res name="Crystals">Q181 1%</res>
    <res name="Eludium">Q130 58%</res>
    <res name="Gems">Q131 1%</res>
    <res name="Ice">Q150 1%</res>
    <res name="Lumenite">Q182 1%</res>
    <res name="Minerals">Q136 1%</res>
    <res name="Natural Gas">Q95 1%</res>
    <res name="Oil">Q159 1%</res>
    <res name="Ore">Q65 1%</res>
    <res name="Radioactives">Q142 1%</res>
    <res name="Stone">Q140 1%</res>
    <res name="Sunlight">Q78 30%</res>
    <res name="Animal Carcass">Q63</res>
    <res name="Beans">Q109</res>
    <res name="Cheese">Q152</res>
    <res name="Eggs">Q82</res>
    <res name="Fertilizer">Q55</res>
    <res name="Fruit">Q158</res>
    <res name="Grain">Q156</res>
    <res name="Grapes">Q194</res>
    <res name="Herbs">Q87</res>
    <res name="Hops">Q197</res>
    <res name="Log">Q28</res>
    <res name="Milk">Q158</res>
    <res name="Nuts">Q193</res>
    <res name="Plant Fiber">Q51</res>
    <res name="Spices">Q132</res>
    <res name="Vegetable">Q119</res>
    <res name="Vegetation Density">Q124</res>
  </body>
  <body name="System FWCTR Beta II" sectorname="" sectorcoords="310, 1, 4" systemname="FWCTR" systemcoords="-2.5, -0.6, 3.8" designation="Beta" type="Planet" diameter="20800m" zone="Frigid" atmosphere="Standard" timestamp="8/11/2012 6:26:59 PM" outofrange="False">
    <res name="Bolite">Q150 1%, Q127 1%, Q184 1%</res>
    <res name="Coal">Q180 1%, Q100 1%, Q61 1%</res>
    <res name="Crystals">Q195 1%, Q109 1%, Q109 1%</res>
    <res name="Gems">Q189 1%, Q145 1%, Q76 1%</res>
    <res name="Ice">Q105 13%, Q93 7%, Q178 7%</res>
    <res name="Lumenite">Q105 1%, Q92 1%, Q117 1%</res>
    <res name="Minerals">Q204 1%, Q152 1%, Q96 1%</res>
    <res name="Natural Gas">Q40 1%, Q122 1%, Q49 1%</res>
    <res name="Oil">Q156 1%, Q89 1%, Q168 1%</res>
    <res name="Ore">Q148 1%, Q118 1%, Q236 1%</res>
    <res name="Polytaride">Q144 1%, Q162 1%, Q81 1%</res>
    <res name="Radioactives">Q119 1%, Q218 1%, Q191 1%</res>
    <res name="Stone">Q190 2%, Q120 2%, Q117 2%</res>
    <res name="Myrathane">Q246 77%</res>
    <res name="Air">Q109 61%</res>
    <res name="Hydrogen">Q152 61%</res>
    <res name="Sunlight">Q84 10%</res>
    <res name="Animal Carcass">Q74, Q104, Q118</res>
    <res name="Beans">Q135, Q167, Q151</res>
    <res name="Cheese">Q63, Q79, Q179</res>
    <res name="Eggs">Q81, Q200, Q180</res>
    <res name="Fertilizer">Q113, Q190, Q202</res>
    <res name="Fruit">Q106, Q134, Q216</res>
    <res name="Grain">Q111, Q162, Q180</res>
    <res name="Grapes">Q154, Q119, Q116</res>
    <res name="Herbs">Q171, Q107, Q99</res>
    <res name="Hops">Q237, Q125, Q124</res>
    <res name="Log">Q171, Q100, Q134</res>
    <res name="Milk">Q123, Q132, Q122</res>
    <res name="Nuts">Q105, Q146, Q17</res>
    <res name="Plant Fiber">Q155, Q85, Q161</res>
    <res name="Spices">Q194, Q121, Q152</res>
    <res name="Vegetable">Q99, Q101, Q185</res>
    <res name="Vegetation Density">Q46, Q146, Q26</res>
  </body>
  <body name="System FWCTR Beta IIa" sectorname="" sectorcoords="310, 1, 4" systemname="FWCTR" systemcoords="-2.5, -0.6, 3.8" designation="Beta" type="Moon" diameter="1900m" zone="Frigid" atmosphere="No Atmosphere" timestamp="8/11/2012 6:26:59 PM" outofrange="False">
    <res name="Coal">Q235 1%</res>
    <res name="Crystals">Q174 1%</res>
    <res name="Eludium">Q89 36%</res>
    <res name="Gems">Q127 1%</res>
    <res name="Ice">Q196 1%</res>
    <res name="Lumenite">Q82 1%</res>
    <res name="Minerals">Q188 1%</res>
    <res name="Natural Gas">Q132 1%</res>
    <res name="Oil">Q97 1%</res>
    <res name="Ore">Q124 1%</res>
    <res name="Radioactives">Q140 1%</res>
    <res name="Stone">Q128 1%</res>
    <res name="Sunlight">Q230 10%</res>
    <res name="Animal Carcass">Q127</res>
    <res name="Beans">Q205</res>
    <res name="Cheese">Q76</res>
    <res name="Eggs">Q136</res>
    <res name="Fertilizer">Q68</res>
    <res name="Fruit">Q78</res>
    <res name="Grain">Q118</res>
    <res name="Grapes">Q123</res>
    <res name="Herbs">Q104</res>
    <res name="Hops">Q158</res>
    <res name="Log">Q206</res>
    <res name="Milk">Q129</res>
    <res name="Nuts">Q136</res>
    <res name="Plant Fiber">Q68</res>
    <res name="Spices">Q130</res>
    <res name="Vegetable">Q157</res>
    <res name="Vegetation Density">Q185</res>
  </body>
  <body name="System FWCTR Beta IIb" sectorname="" sectorcoords="310, 1, 4" systemname="FWCTR" systemcoords="-2.5, -0.6, 3.8" designation="Beta" type="Moon" diameter="3800m" zone="Frigid" atmosphere="No Atmosphere" timestamp="8/11/2012 6:26:59 PM" outofrange="False">
    <res name="Coal">Q150 1%</res>
    <res name="Crystals">Q155 1%</res>
    <res name="Eludium">Q180 64%</res>
    <res name="Gems">Q150 1%</res>
    <res name="Ice">Q39 1%</res>
    <res name="Lumenite">Q120 1%</res>
    <res name="Minerals">Q51 1%</res>
    <res name="Natural Gas">Q87 1%</res>
    <res name="Oil">Q212 1%</res>
    <res name="Ore">Q93 1%</res>
    <res name="Radioactives">Q55 1%</res>
    <res name="Stone">Q194 1%</res>
    <res name="Sunlight">Q119 10%</res>
    <res name="Animal Carcass">Q52</res>
    <res name="Beans">Q147</res>
    <res name="Cheese">Q89</res>
    <res name="Eggs">Q191</res>
    <res name="Fertilizer">Q152</res>
    <res name="Fruit">Q176</res>
    <res name="Grain">Q125</res>
    <res name="Grapes">Q92</res>
    <res name="Herbs">Q166</res>
    <res name="Hops">Q80</res>
    <res name="Log">Q112</res>
    <res name="Milk">Q133</res>
    <res name="Nuts">Q39</res>
    <res name="Plant Fiber">Q108</res>
    <res name="Spices">Q194</res>
    <res name="Vegetable">Q87</res>
    <res name="Vegetation Density">Q68</res>
  </body>
  <body name="System FWCTR Beta IIc" sectorname="" sectorcoords="310, 1, 4" systemname="FWCTR" systemcoords="-2.5, -0.6, 3.8" designation="Beta" type="Moon" diameter="3800m" zone="Frigid" atmosphere="No Atmosphere" timestamp="8/11/2012 6:26:59 PM" outofrange="False">
    <res name="Coal">Q194 1%</res>
    <res name="Crystals">Q134 1%</res>
    <res name="Eludium">Q145 53%</res>
    <res name="Gems">Q171 1%</res>
    <res name="Ice">Q137 1%</res>
    <res name="Lumenite">Q30 1%</res>
    <res name="Minerals">Q171 1%</res>
    <res name="Natural Gas">Q171 1%</res>
    <res name="Oil">Q200 1%</res>
    <res name="Ore">Q62 1%</res>
    <res name="Radioactives">Q225 1%</res>
    <res name="Stone">Q132 1%</res>
    <res name="Sunlight">Q136 10%</res>
    <res name="Animal Carcass">Q105</res>
    <res name="Beans">Q87</res>
    <res name="Cheese">Q101</res>
    <res name="Eggs">Q119</res>
    <res name="Fertilizer">Q106</res>
    <res name="Fruit">Q146</res>
    <res name="Grain">Q130</res>
    <res name="Grapes">Q189</res>
    <res name="Herbs">Q98</res>
    <res name="Hops">Q129</res>
    <res name="Log">Q19</res>
    <res name="Milk">Q138</res>
    <res name="Nuts">Q70</res>
    <res name="Plant Fiber">Q147</res>
    <res name="Spices">Q131</res>
    <res name="Vegetable">Q145</res>
    <res name="Vegetation Density">Q208</res>
  </body>
  <body name="System FWCTR Beta III" sectorname="" sectorcoords="310, 1, 4" systemname="FWCTR" systemcoords="-2.5, -0.6, 3.8" designation="Beta" type="Planet" diameter="11400m" zone="Frigid" atmosphere="Standard" timestamp="8/11/2012 6:26:59 PM" outofrange="False">
    <res name="Bolite">Q142 1%, None, Q138 1%</res>
    <res name="Coal">Q50 1%, Q44 1%, Q125 1%</res>
    <res name="Crystals">Q128 1%, Q69 1%, Q92 1%</res>
    <res name="Gems">Q97 1%, Q137 1%, Q150 1%</res>
    <res name="Ice">Q167 11%, Q118 42%, Q73 9%</res>
    <res name="Lumenite">Q41 1%, Q156 1%, Q213 1%</res>
    <res name="Minerals">Q68 1%, Q146 1%, Q153 1%</res>
    <res name="Natural Gas">Q145 1%, Q85 1%, Q10 1%</res>
    <res name="Oil">Q119 1%, Q177 1%, Q122 1%</res>
    <res name="Ore">Q166 1%, Q235 1%, Q15 1%</res>
    <res name="Radioactives">Q66 1%, Q105 1%, Q207 2%</res>
    <res name="Stone">Q120 2%, Q9 1%, Q95 2%</res>
    <res name="Myrathane">Q125 80%</res>
    <res name="Air">Q71 28%</res>
    <res name="Hydrogen">Q121 28%</res>
    <res name="Sunlight">Q159 10%</res>
    <res name="Animal Carcass">Q170, Q51, Q117</res>
    <res name="Beans">Q55, Q65, Q54</res>
    <res name="Cheese">Q153, Q115, Q204</res>
    <res name="Eggs">Q45, Q34, Q192</res>
    <res name="Fertilizer">Q119, Q63, Q189</res>
    <res name="Fruit">Q194, Q179, Q138</res>
    <res name="Grain">Q92, Q219, Q187</res>
    <res name="Grapes">Q118, Q193, Q109</res>
    <res name="Herbs">Q116, Q113, Q228</res>
    <res name="Hops">Q90, Q86, Q129</res>
    <res name="Log">Q196, Q182, Q99</res>
    <res name="Milk">Q109, Q148, Q208</res>
    <res name="Nuts">Q142, Q159, Q172</res>
    <res name="Plant Fiber">Q164, Q110, Q137</res>
    <res name="Spices">Q129, Q123, Q233</res>
    <res name="Vegetable">Q54, Q97, Q37</res>
    <res name="Vegetation Density">Q140, Q179, Q89</res>
  </body>
  <body name="System FWCTR Beta IIIa" sectorname="" sectorcoords="310, 1, 4" systemname="FWCTR" systemcoords="-2.5, -0.6, 3.8" designation="Beta" type="Moon" diameter="3800m" zone="Frigid" atmosphere="No Atmosphere" timestamp="8/11/2012 6:26:59 PM" outofrange="False">
    <res name="Coal">Q105 1%</res>
    <res name="Crystals">Q107 1%</res>
    <res name="Eludium">Q67 38%</res>
    <res name="Gems">Q61 1%</res>
    <res name="Ice">Q154 1%</res>
    <res name="Lumenite">Q96 1%</res>
    <res name="Minerals">Q84 1%</res>
    <res name="Natural Gas">Q138 1%</res>
    <res name="Oil">Q135 1%</res>
    <res name="Ore">Q88 1%</res>
    <res name="Radioactives">Q139 1%</res>
    <res name="Stone">Q58 1%</res>
    <res name="Sunlight">Q176 10%</res>
    <res name="Animal Carcass">Q96</res>
    <res name="Beans">Q125</res>
    <res name="Cheese">Q165</res>
    <res name="Eggs">Q100</res>
    <res name="Fertilizer">Q203</res>
    <res name="Fruit">Q165</res>
    <res name="Grain">Q99</res>
    <res name="Grapes">Q216</res>
    <res name="Herbs">Q49</res>
    <res name="Hops">Q139</res>
    <res name="Log">Q103</res>
    <res name="Milk">Q114</res>
    <res name="Nuts">Q172</res>
    <res name="Plant Fiber">Q203</res>
    <res name="Spices">Q194</res>
    <res name="Vegetable">Q240</res>
    <res name="Vegetation Density">Q23</res>
  </body>
  <body name="System FWCTR Beta IIIb" sectorname="" sectorcoords="310, 1, 4" systemname="FWCTR" systemcoords="-2.5, -0.6, 3.8" designation="Beta" type="Moon" diameter="1900m" zone="Frigid" atmosphere="No Atmosphere" timestamp="8/11/2012 6:26:59 PM" outofrange="False">
    <res name="Coal">Q19 1%</res>
    <res name="Crystals">Q87 1%</res>
    <res name="Eludium">Q160 47%</res>
    <res name="Gems">Q212 1%</res>
    <res name="Ice">Q125 1%</res>
    <res name="Lumenite">Q134 1%</res>
    <res name="Minerals">Q204 1%</res>
    <res name="Natural Gas">Q93 1%</res>
    <res name="Oil">Q122 1%</res>
    <res name="Ore">Q185 1%</res>
    <res name="Radioactives">Q182 1%</res>
    <res name="Stone">Q124 1%</res>
    <res name="Sunlight">Q66 10%</res>
    <res name="Animal Carcass">Q149</res>
    <res name="Beans">Q65</res>
    <res name="Cheese">Q178</res>
    <res name="Eggs">Q155</res>
    <res name="Fertilizer">Q30</res>
    <res name="Fruit">Q136</res>
    <res name="Grain">Q106</res>
    <res name="Grapes">Q185</res>
    <res name="Herbs">Q110</res>
    <res name="Hops">Q61</res>
    <res name="Log">Q136</res>
    <res name="Milk">Q118</res>
    <res name="Nuts">Q75</res>
    <res name="Plant Fiber">Q115</res>
    <res name="Spices">Q130</res>
    <res name="Vegetable">Q170</res>
    <res name="Vegetation Density">Q163</res>
  </body>
  <body name="System FWCTR Alpha I" sectorname="" sectorcoords="310, 1, 4" systemname="FWCTR" systemcoords="-2.5, -0.6, 3.8" designation="Alpha" type="Planet" diameter="17000m" zone="Habitable" atmosphere="Standard" timestamp="8/11/2012 6:26:59 PM" outofrange="False">
    <res name="Coal">Q61 1%, Q160 1%, Q102 1%</res>
    <res name="Crystals">Q174 1%, Q200 1%, Q88 1%</res>
    <res name="Gems">Q135 1%, Q111 1%, Q76 1%</res>
    <res name="Ice">Q135 4%, Q15 4%, Q123 5%</res>
    <res name="Minerals">Q152 1%, Q161 1%, Q181 1%</res>
    <res name="Natural Gas">Q75 1%, Q113 1%, Q45 1%</res>
    <res name="Oil">Q105 1%, Q148 1%, Q150 1%</res>
    <res name="Ore">Q197 1%, Q159 1%, Q27 2%</res>
    <res name="Radioactives">Q202 1%, Q67 1%, Q147 1%</res>
    <res name="Stone">Q89 2%, Q176 2%, Q186 2%</res>
    <res name="Water in the Environment">Q90 78%</res>
    <res name="Air">Q141 64%</res>
    <res name="Hydrogen">Q204 64%</res>
    <res name="Sunlight">Q147 50%</res>
    <res name="Animal Carcass">Q170, Q108, Q208</res>
    <res name="Beans">Q98, Q112, Q229</res>
    <res name="Cheese">Q162, Q156, Q158</res>
    <res name="Eggs">Q108, Q24, Q45</res>
    <res name="Fertilizer">Q134, Q210, Q181</res>
    <res name="Fish">Q159, Q103, Q126</res>
    <res name="Fruit">Q141, Q88, Q93</res>
    <res name="Grain">Q138, Q41, Q202</res>
    <res name="Grapes">Q82, Q124, Q74</res>
    <res name="Herbs">Q127, Q168, Q211</res>
    <res name="Hops">Q81, Q107, Q133</res>
    <res name="Log">Q80, Q59, Q236</res>
    <res name="Milk">Q127, Q34, Q59</res>
    <res name="Nuts">Q128, Q56, Q197</res>
    <res name="Plant Fiber">Q171, Q79, Q53</res>
    <res name="Spices">Q48, Q133, Q42</res>
    <res name="Vegetable">Q94, Q147, Q91</res>
    <res name="Vegetation Density">Q51, Q149, Q94</res>
  </body>
  <body name="System FWCTR Alpha II" sectorname="" sectorcoords="310, 1, 4" systemname="FWCTR" systemcoords="-2.5, -0.6, 3.8" designation="Alpha" type="Planet" diameter="11400m" zone="Outer" atmosphere="Tainted" timestamp="8/11/2012 6:26:59 PM" outofrange="False">
    <res name="Coal">Q208 1%, Q115 1%, Q121 1%</res>
    <res name="Crystals">Q148 1%, Q173 1%, Q120 1%</res>
    <res name="Gems">Q181 1%, Q178 1%, Q231 1%</res>
    <res name="Ice">Q137 5%, Q81 27%, Q82 22%</res>
    <res name="Lumenite">Q114 1%, Q141 1%, Q142 1%</res>
    <res name="Minerals">Q93 1%, Q162 1%, Q28 1%</res>
    <res name="Natural Gas">Q28 1%, Q34 1%, Q96 1%</res>
    <res name="Oil">Q86 1%, Q152 1%, Q68 1%</res>
    <res name="Ore">Q39 1%, Q129 1%, Q137 1%</res>
    <res name="Radioactives">Q55 1%, Q193 1%, Q208 1%</res>
    <res name="Stone">Q127 2%, Q54 1%, Q210 1%</res>
    <res name="Water in the Environment">Q131 61%</res>
    <res name="Air">Q89 77%</res>
    <res name="Hydrogen">Q141 77%</res>
    <res name="Sunlight">Q124 30%</res>
    <res name="Animal Carcass">Q116, Q134, Q137</res>
    <res name="Beans">Q171, Q169, Q80</res>
    <res name="Cheese">Q150, Q156, Q221</res>
    <res name="Eggs">Q209, Q101, Q148</res>
    <res name="Fertilizer">Q226, Q118, Q109</res>
    <res name="Fish">Q22, Q73, Q116</res>
    <res name="Fruit">Q202, Q122, Q156</res>
    <res name="Grain">Q121, Q143, Q132</res>
    <res name="Grapes">Q169, Q103, Q94</res>
    <res name="Herbs">Q129, Q149, Q62</res>
    <res name="Hops">Q52, Q153, Q129</res>
    <res name="Log">Q156, Q93, Q139</res>
    <res name="Milk">Q77, Q56, Q194</res>
    <res name="Nuts">Q192, Q71, Q154</res>
    <res name="Plant Fiber">Q124, Q81, Q182</res>
    <res name="Spices">Q131, Q58, Q124</res>
    <res name="Vegetable">Q81, Q143, Q143</res>
    <res name="Vegetation Density">Q118, Q73, Q30</res>
  </body>
  <body name="System FWCTR Alpha IIa" sectorname="" sectorcoords="310, 1, 4" systemname="FWCTR" systemcoords="-2.5, -0.6, 3.8" designation="Alpha" type="Moon" diameter="3800m" zone="Outer" atmosphere="No Atmosphere" timestamp="8/11/2012 6:26:59 PM" outofrange="False">
    <res name="Coal">Q50 1%</res>
    <res name="Crystals">Q147 1%</res>
    <res name="Eludium">Q139 50%</res>
    <res name="Gems">Q145 1%</res>
    <res name="Ice">Q85 1%</res>
    <res name="Lumenite">Q148 1%</res>
    <res name="Minerals">Q101 1%</res>
    <res name="Natural Gas">Q137 1%</res>
    <res name="Oil">Q191 1%</res>
    <res name="Ore">Q150 1%</res>
    <res name="Radioactives">Q181 1%</res>
    <res name="Stone">Q53 1%</res>
    <res name="Sunlight">Q142 30%</res>
    <res name="Animal Carcass">Q117</res>
    <res name="Beans">Q113</res>
    <res name="Cheese">Q140</res>
    <res name="Eggs">Q118</res>
    <res name="Fertilizer">Q164</res>
    <res name="Fruit">Q95</res>
    <res name="Grain">Q86</res>
    <res name="Grapes">Q149</res>
    <res name="Herbs">Q183</res>
    <res name="Hops">Q169</res>
    <res name="Log">Q161</res>
    <res name="Milk">Q233</res>
    <res name="Nuts">Q110</res>
    <res name="Plant Fiber">Q124</res>
    <res name="Spices">Q193</res>
    <res name="Vegetable">Q124</res>
    <res name="Vegetation Density">Q129</res>
  </body>
  <body name="System FWCTR Alpha III" sectorname="" sectorcoords="310, 1, 4" systemname="FWCTR" systemcoords="-2.5, -0.6, 3.8" designation="Alpha" type="Planet" diameter="18900m" zone="Frigid" atmosphere="Insidious" timestamp="8/11/2012 6:26:59 PM" outofrange="False">
    <res name="Bolite">Q164 1%, Q71 1%, Q118 1%</res>
    <res name="Coal">Q174 1%, Q129 1%, Q187 1%</res>
    <res name="Crystals">Q141 1%, Q189 1%, Q183 1%</res>
    <res name="Gems">Q93 1%, Q115 1%, Q151 1%</res>
    <res name="Ice">Q141 11%, Q91 5%, Q209 4%</res>
    <res name="Lumenite">Q149 1%, Q220 1%, Q223 1%</res>
    <res name="Minerals">Q92 1%, Q131 1%, Q115 1%</res>
    <res name="Natural Gas">Q90 1%, Q127 1%, Q132 1%</res>
    <res name="Oil">Q117 1%, Q170 1%, Q54 1%</res>
    <res name="Ore">Q124 1%, Q123 1%, Q96 1%</res>
    <res name="Polytaride">Q131 1%, Q121 1%, Q150 1%</res>
    <res name="Radioactives">Q238 1%, Q183 1%, Q159 2%</res>
    <res name="Stone">Q170 2%, Q178 2%, Q128 2%</res>
    <res name="Myrathane">Q98 55%</res>
    <res name="Air">Q69 76%</res>
    <res name="Cryozine">Q199 4%</res>
    <res name="Hydrogen">Q129 76%</res>
    <res name="Sunlight">Q37 10%</res>
    <res name="Animal Carcass">Q181, Q183, Q198</res>
    <res name="Beans">Q209, Q168, Q83</res>
    <res name="Cheese">Q64, Q27, Q135</res>
    <res name="Eggs">Q173, Q118, Q135</res>
    <res name="Fertilizer">Q177, Q109, Q161</res>
    <res name="Fruit">Q142, Q27, Q82</res>
    <res name="Grain">Q176, Q139, Q117</res>
    <res name="Grapes">Q77, Q65, Q135</res>
    <res name="Herbs">Q199, Q168, Q59</res>
    <res name="Hops">Q131, Q125, Q99</res>
    <res name="Log">Q83, Q74, Q62</res>
    <res name="Milk">Q75, Q144, Q107</res>
    <res name="Nuts">Q182, Q102, Q193</res>
    <res name="Plant Fiber">Q140, Q126, Q166</res>
    <res name="Spices">Q64, Q168, Q78</res>
    <res name="Vegetable">Q161, Q217, Q120</res>
    <res name="Vegetation Density">Q190, Q85, Q154</res>
  </body>
  <body name="System FWCTR Alpha IIIa" sectorname="" sectorcoords="310, 1, 4" systemname="FWCTR" systemcoords="-2.5, -0.6, 3.8" designation="Alpha" type="Moon" diameter="3800m" zone="Frigid" atmosphere="No Atmosphere" timestamp="8/11/2012 6:26:59 PM" outofrange="False">
    <res name="Coal">Q184 1%</res>
    <res name="Crystals">Q120 1%</res>
    <res name="Eludium">Q62 58%</res>
    <res name="Gems">Q35 1%</res>
    <res name="Ice">Q101 1%</res>
    <res name="Lumenite">Q86 1%</res>
    <res name="Minerals">Q144 1%</res>
    <res name="Natural Gas">Q192 1%</res>
    <res name="Oil">Q95 1%</res>
    <res name="Ore">Q176 1%</res>
    <res name="Radioactives">Q94 1%</res>
    <res name="Stone">Q107 1%</res>
    <res name="Sunlight">Q54 10%</res>
    <res name="Animal Carcass">Q106</res>
    <res name="Beans">Q22</res>
    <res name="Cheese">Q76</res>
    <res name="Eggs">Q100</res>
    <res name="Fertilizer">Q132</res>
    <res name="Fruit">Q241</res>
    <res name="Grain">Q183</res>
    <res name="Grapes">Q47</res>
    <res name="Herbs">Q133</res>
    <res name="Hops">Q51</res>
    <res name="Log">Q117</res>
    <res name="Milk">Q207</res>
    <res name="Nuts">Q213</res>
    <res name="Plant Fiber">Q52</res>
    <res name="Spices">Q128</res>
    <res name="Vegetable">Q91</res>
    <res name="Vegetation Density">Q73</res>
  </body>
  <body name="System FWCTR Alpha IIIb" sectorname="" sectorcoords="310, 1, 4" systemname="FWCTR" systemcoords="-2.5, -0.6, 3.8" designation="Alpha" type="Moon" diameter="3800m" zone="Frigid" atmosphere="No Atmosphere" timestamp="8/11/2012 6:26:59 PM" outofrange="False">
    <res name="Coal">Q100 1%</res>
    <res name="Crystals">Q101 1%</res>
    <res name="Eludium">Q154 45%</res>
    <res name="Gems">Q184 1%</res>
    <res name="Ice">Q200 1%</res>
    <res name="Lumenite">Q252 1%</res>
    <res name="Minerals">Q136 1%</res>
    <res name="Natural Gas">Q147 1%</res>
    <res name="Oil">Q210 1%</res>
    <res name="Ore">Q145 1%</res>
    <res name="Radioactives">Q137 1%</res>
    <res name="Stone">Q173 1%</res>
    <res name="Sunlight">Q200 10%</res>
    <res name="Animal Carcass">Q160</res>
    <res name="Beans">Q91</res>
    <res name="Cheese">Q89</res>
    <res name="Eggs">Q154</res>
    <res name="Fertilizer">Q88</res>
    <res name="Fruit">Q84</res>
    <res name="Grain">Q188</res>
    <res name="Grapes">Q16</res>
    <res name="Herbs">Q193</res>
    <res name="Hops">Q100</res>
    <res name="Log">Q152</res>
    <res name="Milk">Q85</res>
    <res name="Nuts">Q116</res>
    <res name="Plant Fiber">Q92</res>
    <res name="Spices">Q64</res>
    <res name="Vegetable">Q149</res>
    <res name="Vegetation Density">Q212</res>
  </body>
  <body name="System FWCTR Alpha IV" sectorname="" sectorcoords="310, 1, 4" systemname="FWCTR" systemcoords="-2.5, -0.6, 3.8" designation="Alpha" type="Gas Giant" diameter="53000m" zone="Frigid" atmosphere="Exotic" timestamp="8/11/2012 6:26:59 PM" outofrange="False">
    <res name="Air">Q106 93%</res>
    <res name="Borexino Precipitate">Q183 1%</res>
    <res name="Cryozine">Q103 2%</res>
    <res name="Hydrogen">Q162 93%</res>
    <res name="Sunlight">Q89 10%</res>
  </body>
  <body name="System FWCTR Alpha IVa" sectorname="" sectorcoords="310, 1, 4" systemname="FWCTR" systemcoords="-2.5, -0.6, 3.8" designation="Alpha" type="Moon" diameter="3800m" zone="Frigid" atmosphere="No Atmosphere" timestamp="8/11/2012 6:26:59 PM" outofrange="False">
    <res name="Coal">Q187 1%</res>
    <res name="Crystals">Q61 1%</res>
    <res name="Eludium">Q210 28%</res>
    <res name="Gems">Q101 1%</res>
    <res name="Ice">Q142 1%</res>
    <res name="Lumenite">Q200 1%</res>
    <res name="Minerals">Q118 1%</res>
    <res name="Natural Gas">Q59 1%</res>
    <res name="Oil">Q185 1%</res>
    <res name="Ore">Q84 1%</res>
    <res name="Radioactives">Q95 1%</res>
    <res name="Stone">Q178 1%</res>
    <res name="Sunlight">Q107 10%</res>
    <res name="Animal Carcass">Q138</res>
    <res name="Beans">Q103</res>
    <res name="Cheese">Q115</res>
    <res name="Eggs">Q8</res>
    <res name="Fertilizer">Q126</res>
    <res name="Fruit">Q153</res>
    <res name="Grain">Q201</res>
    <res name="Grapes">Q83</res>
    <res name="Herbs">Q61</res>
    <res name="Hops">Q199</res>
    <res name="Log">Q92</res>
    <res name="Milk">Q94</res>
    <res name="Nuts">Q177</res>
    <res name="Plant Fiber">Q44</res>
    <res name="Spices">Q65</res>
    <res name="Vegetable">Q137</res>
    <res name="Vegetation Density">Q234</res>
  </body>
</database>