<?xml version="1.0" encoding="utf-8" standalone="yes"?>
<database application="Hazeron Scouter" version="0.3.3.4">
  <body name="M3 Ib Weaker Supergiant Alpha" sectorname="" sectorcoords="309, 1, 5" systemname="YCIUR" systemcoords="3.9, -1.9, -2.2" designation="Alpha" type="Star" diameter="1.5au" zone="" atmosphere="None" timestamp="8/11/2012 6:39:10 PM" outofrange="False">
    <res name="Type M Preons">Q74 5%</res>
  </body>
  <body name="A8 Ib Weaker Supergiant Beta" sectorname="" sectorcoords="309, 1, 5" systemname="YCIUR" systemcoords="3.9, -1.9, -2.2" designation="Alpha" type="Star" diameter="0.125au" zone="" atmosphere="None" timestamp="8/11/2012 6:39:10 PM" outofrange="False">
    <res name="Type A Preons">Q195 5%</res>
  </body>
  <body name="System YCIUR Alpha I" sectorname="" sectorcoords="309, 1, 5" systemname="YCIUR" systemcoords="3.9, -1.9, -2.2" designation="Alpha" type="Planet" diameter="5700m" zone="Inferno" atmosphere="Standard" timestamp="8/11/2012 6:39:10 PM" outofrange="False">
    <res name="Crystals">Q150 1%, Q155 1%, Q87 1%</res>
    <res name="Eludium">Q197 59%, Q124 16%, Q76 24%</res>
    <res name="Gems">Q46 1%, Q106 1%, Q68 1%</res>
    <res name="Minerals">Q85 1%, Q102 1%, Q238 1%</res>
    <res name="Ore">Q181 1%, Q30 1%, Q229 1%</res>
    <res name="Radioactives">Q158 1%, Q56 1%, Q155 1%</res>
    <res name="Stone">Q60 1%, Q106 1%, Q191 1%</res>
    <res name="Magmex">Q160 17%</res>
    <res name="Air">Q207 4%</res>
    <res name="Hydrogen">Q80 4%</res>
    <res name="Sunlight">Q124 90%</res>
    <res name="Animal Carcass">Q104, Q30, Q83</res>
    <res name="Beans">Q169, Q39, Q34</res>
    <res name="Cheese">Q72, Q97, Q153</res>
    <res name="Eggs">Q82, Q19, Q106</res>
    <res name="Fertilizer">Q29, Q162, Q240</res>
    <res name="Fruit">Q119, Q238, Q116</res>
    <res name="Grain">Q29, Q166, Q90</res>
    <res name="Grapes">Q180, Q149, Q126</res>
    <res name="Herbs">Q163, Q59, Q128</res>
    <res name="Hops">Q74, Q94, Q109</res>
    <res name="Log">Q142, Q156, Q210</res>
    <res name="Milk">Q135, Q154, Q138</res>
    <res name="Nuts">Q130, Q152, Q164</res>
    <res name="Plant Fiber">Q155, Q180, Q59</res>
    <res name="Spices">Q25, Q132, Q109</res>
    <res name="Vegetable">Q121, Q131, Q206</res>
    <res name="Vegetation Density">Q62, Q66, Q101</res>
  </body>
  <body name="System YCIUR Alpha II" sectorname="" sectorcoords="309, 1, 5" systemname="YCIUR" systemcoords="3.9, -1.9, -2.2" designation="Alpha" type="Planet" diameter="13300m" zone="Inferno" atmosphere="Tainted" timestamp="8/11/2012 6:39:10 PM" outofrange="False">
    <res name="Crystals">Q156 1%, Q122 1%, Q133 1%</res>
    <res name="Gems">Q47 1%, Q165 1%, Q60 1%</res>
    <res name="Minerals">Q92 2%, Q86 1%, Q88 1%</res>
    <res name="Ore">Q114 1%, Q155 1%, Q112 1%</res>
    <res name="Phlogiston">None, Q149 1%, None</res>
    <res name="Radioactives">Q133 1%, Q120 1%, Q55 2%</res>
    <res name="Stone">Q201 2%, Q77 2%, Q50 2%</res>
    <res name="Vulcanite">None, Q137 1%, Q78 1%</res>
    <res name="Magmex">Q242 39%</res>
    <res name="Air">Q154 24%</res>
    <res name="Hydrogen">Q18 24%</res>
    <res name="Sunlight">Q228 90%</res>
    <res name="Animal Carcass">Q39, Q132, Q193</res>
    <res name="Beans">Q73, Q69, Q74</res>
    <res name="Cheese">Q148, Q27, Q96</res>
    <res name="Eggs">Q156, Q104, Q209</res>
    <res name="Fertilizer">Q143, Q111, Q143</res>
    <res name="Fruit">Q200, Q100, Q69</res>
    <res name="Grain">Q195, Q172, Q56</res>
    <res name="Grapes">Q124, Q115, Q99</res>
    <res name="Herbs">Q146, Q98, Q169</res>
    <res name="Hops">Q113, Q97, Q73</res>
    <res name="Log">Q92, Q208, Q140</res>
    <res name="Milk">Q164, Q140, Q51</res>
    <res name="Nuts">Q58, Q108, Q127</res>
    <res name="Plant Fiber">Q138, Q114, Q191</res>
    <res name="Spices">Q154, Q133, Q174</res>
    <res name="Vegetable">Q83, Q121, Q213</res>
    <res name="Vegetation Density">Q129, Q54, Q186</res>
  </body>
  <body name="System YCIUR Alpha III" sectorname="" sectorcoords="309, 1, 5" systemname="YCIUR" systemcoords="3.9, -1.9, -2.2" designation="Alpha" type="Gas Giant" diameter="68200m" zone="Inferno" atmosphere="Insidious" timestamp="8/11/2012 6:39:10 PM" outofrange="False">
    <res name="Air">Q114 98%</res>
    <res name="Borexino Precipitate">Q210 2%</res>
    <res name="Hydrogen">Q122 98%</res>
    <res name="Ioplasma">Q155 5%</res>
    <res name="Sunlight">Q53 90%</res>
  </body>
  <body name="System YCIUR Alpha IIIa" sectorname="" sectorcoords="309, 1, 5" systemname="YCIUR" systemcoords="3.9, -1.9, -2.2" designation="Alpha" type="Moon" diameter="3800m" zone="Inferno" atmosphere="No Atmosphere" timestamp="8/11/2012 6:39:10 PM" outofrange="False">
    <res name="Crystals">Q169 1%</res>
    <res name="Eludium">Q233 26%</res>
    <res name="Gems">Q152 1%</res>
    <res name="Minerals">Q125 1%</res>
    <res name="Ore">Q102 1%</res>
    <res name="Radioactives">Q183 1%</res>
    <res name="Stone">Q122 1%</res>
    <res name="Sunlight">Q106 90%</res>
    <res name="Animal Carcass">Q179</res>
    <res name="Beans">Q99</res>
    <res name="Cheese">Q59</res>
    <res name="Eggs">Q156</res>
    <res name="Fertilizer">Q201</res>
    <res name="Fruit">Q148</res>
    <res name="Grain">Q23</res>
    <res name="Grapes">Q211</res>
    <res name="Herbs">Q103</res>
    <res name="Hops">Q152</res>
    <res name="Log">Q107</res>
    <res name="Milk">Q130</res>
    <res name="Nuts">Q99</res>
    <res name="Plant Fiber">Q115</res>
    <res name="Spices">Q88</res>
    <res name="Vegetable">Q191</res>
    <res name="Vegetation Density">Q179</res>
  </body>
  <body name="System YCIUR Alpha IIIbr (1)" sectorname="" sectorcoords="309, 1, 5" systemname="YCIUR" systemcoords="3.9, -1.9, -2.2" designation="Alpha" type="Ring" diameter="59200m" zone="Inferno" atmosphere="None" timestamp="8/11/2012 6:39:10 PM" outofrange="False">
    <res name="Crystals">Q62 1%</res>
    <res name="Eludium">Q141 50%</res>
    <res name="Gems">Q130 1%</res>
    <res name="Lumenite">Q186 1%</res>
    <res name="Minerals">Q100 1%</res>
    <res name="Ore">Q176 1%</res>
    <res name="Radioactives">Q26 1%</res>
    <res name="Stone">Q185 1%</res>
    <res name="Antiflux Particles">Q55 4%</res>
    <res name="Sunlight">Q89 90%</res>
  </body>
  <body name="System YCIUR Alpha IIIb" sectorname="" sectorcoords="309, 1, 5" systemname="YCIUR" systemcoords="3.9, -1.9, -2.2" designation="Alpha" type="Moon" diameter="3800m" zone="Inferno" atmosphere="No Atmosphere" timestamp="8/11/2012 6:39:10 PM" outofrange="False">
    <res name="Crystals">Q81 1%</res>
    <res name="Eludium">Q176 42%</res>
    <res name="Gems">Q107 1%</res>
    <res name="Minerals">Q78 1%</res>
    <res name="Ore">Q200 1%</res>
    <res name="Radioactives">Q233 1%</res>
    <res name="Stone">Q119 1%</res>
    <res name="Sunlight">Q198 90%</res>
    <res name="Animal Carcass">Q72</res>
    <res name="Beans">Q215</res>
    <res name="Cheese">Q161</res>
    <res name="Eggs">Q174</res>
    <res name="Fertilizer">Q163</res>
    <res name="Fruit">Q78</res>
    <res name="Grain">Q138</res>
    <res name="Grapes">Q144</res>
    <res name="Herbs">Q109</res>
    <res name="Hops">Q183</res>
    <res name="Log">Q166</res>
    <res name="Milk">Q248</res>
    <res name="Nuts">Q166</res>
    <res name="Plant Fiber">Q163</res>
    <res name="Spices">Q88</res>
    <res name="Vegetable">Q75</res>
    <res name="Vegetation Density">Q157</res>
  </body>
  <body name="System YCIUR Alpha IV" sectorname="" sectorcoords="309, 1, 5" systemname="YCIUR" systemcoords="3.9, -1.9, -2.2" designation="Alpha" type="Planet" diameter="17000m" zone="Inner" atmosphere="Standard" timestamp="8/11/2012 6:39:10 PM" outofrange="False">
    <res name="Coal">Q55 1%, Q66 1%, Q145 1%</res>
    <res name="Crystals">Q173 2%, Q185 1%, Q229 1%</res>
    <res name="Gems">Q84 1%, Q144 1%, Q66 1%</res>
    <res name="Ice">Q243 1%, Q112 12%, Q219 11%</res>
    <res name="Minerals">Q97 2%, Q178 1%, Q116 1%</res>
    <res name="Natural Gas">Q160 1%, Q170 1%, Q63 2%</res>
    <res name="Oil">Q44 1%, Q139 1%, Q93 2%</res>
    <res name="Ore">Q115 1%, Q88 1%, Q211 1%</res>
    <res name="Radioactives">Q160 1%, Q123 1%, Q103 1%</res>
    <res name="Stone">Q195 2%, Q237 1%, Q97 1%</res>
    <res name="Water in the Environment">Q106 60%</res>
    <res name="Air">Q134 96%</res>
    <res name="Hydrogen">Q134 96%</res>
    <res name="Sunlight">Q13 70%</res>
    <res name="Animal Carcass">Q127, Q27, Q103</res>
    <res name="Beans">Q155, Q70, Q180</res>
    <res name="Cheese">Q126, Q67, Q102</res>
    <res name="Eggs">Q152, Q94, Q91</res>
    <res name="Fertilizer">Q56, Q53, Q86</res>
    <res name="Fish">Q164, Q182, Q60</res>
    <res name="Fruit">Q88, Q118, Q133</res>
    <res name="Grain">Q97, Q34, Q182</res>
    <res name="Grapes">Q198, Q88, Q28</res>
    <res name="Herbs">Q89, Q115, Q52</res>
    <res name="Hops">Q143, Q170, Q189</res>
    <res name="Log">Q135, Q35, Q155</res>
    <res name="Milk">Q63, Q143, Q158</res>
    <res name="Nuts">Q158, Q152, Q72</res>
    <res name="Plant Fiber">Q218, Q110, Q208</res>
    <res name="Spices">Q157, Q69, Q233</res>
    <res name="Vegetable">Q112, Q167, Q101</res>
    <res name="Vegetation Density">Q202, Q171, Q145</res>
  </body>
  <body name="System YCIUR Alpha IVa" sectorname="" sectorcoords="309, 1, 5" systemname="YCIUR" systemcoords="3.9, -1.9, -2.2" designation="Alpha" type="Moon" diameter="3800m" zone="Inner" atmosphere="No Atmosphere" timestamp="8/11/2012 6:39:10 PM" outofrange="False">
    <res name="Coal">Q195 1%</res>
    <res name="Crystals">Q108 1%</res>
    <res name="Eludium">Q126 55%</res>
    <res name="Gems">Q90 1%</res>
    <res name="Ice">Q32 1%</res>
    <res name="Minerals">Q194 1%</res>
    <res name="Natural Gas">Q196 1%</res>
    <res name="Oil">Q149 1%</res>
    <res name="Ore">Q181 1%</res>
    <res name="Radioactives">Q70 1%</res>
    <res name="Stone">Q65 1%</res>
    <res name="Sunlight">Q159 70%</res>
    <res name="Animal Carcass">Q83</res>
    <res name="Beans">Q179</res>
    <res name="Cheese">Q97</res>
    <res name="Eggs">Q65</res>
    <res name="Fertilizer">Q66</res>
    <res name="Fruit">Q60</res>
    <res name="Grain">Q171</res>
    <res name="Grapes">Q119</res>
    <res name="Herbs">Q158</res>
    <res name="Hops">Q172</res>
    <res name="Log">Q82</res>
    <res name="Milk">Q16</res>
    <res name="Nuts">Q191</res>
    <res name="Plant Fiber">Q106</res>
    <res name="Spices">Q153</res>
    <res name="Vegetable">Q108</res>
    <res name="Vegetation Density">Q85</res>
  </body>
  <body name="System YCIUR Alpha V" sectorname="" sectorcoords="309, 1, 5" systemname="YCIUR" systemcoords="3.9, -1.9, -2.2" designation="Alpha" type="Gas Giant" diameter="53000m" zone="Habitable" atmosphere="Corrosive" timestamp="8/11/2012 6:39:10 PM" outofrange="False">
    <res name="Air">Q184 98%</res>
    <res name="Borexino Precipitate">Q174 1%</res>
    <res name="Hydrogen">Q78 98%</res>
    <res name="Sunlight">Q170 50%</res>
  </body>
  <body name="System YCIUR Alpha Va" sectorname="" sectorcoords="309, 1, 5" systemname="YCIUR" systemcoords="3.9, -1.9, -2.2" designation="Alpha" type="Moon" diameter="1900m" zone="Habitable" atmosphere="No Atmosphere" timestamp="8/11/2012 6:39:10 PM" outofrange="False">
    <res name="Coal">Q188 1%</res>
    <res name="Crystals">Q96 1%</res>
    <res name="Eludium">Q170 35%</res>
    <res name="Gems">Q81 1%</res>
    <res name="Ice">Q123 1%</res>
    <res name="Lumenite">Q138 1%</res>
    <res name="Minerals">Q168 1%</res>
    <res name="Natural Gas">Q229 1%</res>
    <res name="Oil">Q126 1%</res>
    <res name="Ore">Q167 1%</res>
    <res name="Radioactives">Q66 1%</res>
    <res name="Stone">Q168 1%</res>
    <res name="Sunlight">Q76 50%</res>
    <res name="Animal Carcass">Q83</res>
    <res name="Beans">Q113</res>
    <res name="Cheese">Q72</res>
    <res name="Eggs">Q46</res>
    <res name="Fertilizer">Q93</res>
    <res name="Fruit">Q27</res>
    <res name="Grain">Q94</res>
    <res name="Grapes">Q103</res>
    <res name="Herbs">Q192</res>
    <res name="Hops">Q94</res>
    <res name="Log">Q53</res>
    <res name="Milk">Q86</res>
    <res name="Nuts">Q79</res>
    <res name="Plant Fiber">Q140</res>
    <res name="Spices">Q151</res>
    <res name="Vegetable">Q183</res>
    <res name="Vegetation Density">Q206</res>
  </body>
  <body name="System YCIUR Alpha Vb" sectorname="" sectorcoords="309, 1, 5" systemname="YCIUR" systemcoords="3.9, -1.9, -2.2" designation="Alpha" type="Large Moon" diameter="9500m" zone="Habitable" atmosphere="Standard" timestamp="8/11/2012 6:39:10 PM" outofrange="False">
    <res name="Coal">Q168 1%, Q121 1%, Q109 1%</res>
    <res name="Crystals">Q110 1%, Q180 1%, Q79 1%</res>
    <res name="Gems">Q174 2%, Q106 1%, Q148 2%</res>
    <res name="Ice">Q151 3%, Q99 3%, Q103 3%</res>
    <res name="Minerals">Q195 1%, Q65 1%, Q162 1%</res>
    <res name="Natural Gas">Q135 1%, Q67 1%, Q95 1%</res>
    <res name="Oil">Q203 1%, Q236 1%, Q127 1%</res>
    <res name="Ore">Q168 1%, Q138 2%, Q99 1%</res>
    <res name="Radioactives">Q79 1%, Q212 1%, Q156 1%</res>
    <res name="Stone">Q160 2%, Q62 2%, Q205 2%</res>
    <res name="Water in the Environment">Q138 42%</res>
    <res name="Air">Q111 70%</res>
    <res name="Hydrogen">Q132 70%</res>
    <res name="Sunlight">Q187 50%</res>
    <res name="Animal Carcass">Q53, Q142, Q195</res>
    <res name="Beans">Q138, Q118, Q226</res>
    <res name="Cheese">Q115, Q95, Q89</res>
    <res name="Eggs">Q159, Q156, Q149</res>
    <res name="Fertilizer">Q206, Q197, Q109</res>
    <res name="Fish">Q152, Q64, Q152</res>
    <res name="Fruit">Q95, Q212, Q152</res>
    <res name="Grain">Q131, Q27, Q232</res>
    <res name="Grapes">Q152, Q199, Q61</res>
    <res name="Herbs">Q86, Q108, Q102</res>
    <res name="Hops">Q74, Q128, Q157</res>
    <res name="Log">Q238, Q56, Q114</res>
    <res name="Milk">Q168, Q140, Q135</res>
    <res name="Nuts">Q158, Q137, Q149</res>
    <res name="Plant Fiber">Q55, Q194, Q181</res>
    <res name="Spices">Q121, Q105, Q106</res>
    <res name="Vegetable">Q137, Q64, Q126</res>
    <res name="Vegetation Density">Q68, Q36, Q152</res>
  </body>
  <body name="System YCIUR Alpha VI" sectorname="" sectorcoords="309, 1, 5" systemname="YCIUR" systemcoords="3.9, -1.9, -2.2" designation="Alpha" type="Planet" diameter="20800m" zone="Outer" atmosphere="Standard" timestamp="8/11/2012 6:39:10 PM" outofrange="False">
    <res name="Coal">Q142 1%, Q160 1%, Q123 2%</res>
    <res name="Crystals">Q93 1%, Q77 1%, Q123 1%</res>
    <res name="Gems">Q150 2%, Q135 1%, Q122 1%</res>
    <res name="Ice">Q24 11%, Q123 8%, Q89 34%</res>
    <res name="Lumenite">Q89 1%, None, None</res>
    <res name="Minerals">Q118 1%, Q116 1%, Q146 1%</res>
    <res name="Natural Gas">Q78 1%, Q227 1%, Q81 2%</res>
    <res name="Oil">Q166 1%, Q158 1%, Q114 2%</res>
    <res name="Ore">Q85 1%, Q145 1%, Q219 1%</res>
    <res name="Radioactives">Q69 1%, Q129 1%, Q184 1%</res>
    <res name="Stone">Q109 2%, Q117 2%, Q154 1%</res>
    <res name="Water in the Environment">Q184 79%</res>
    <res name="Air">Q117 60%</res>
    <res name="Hydrogen">Q113 60%</res>
    <res name="Sunlight">Q176 30%</res>
    <res name="Animal Carcass">Q131, Q76, Q190</res>
    <res name="Beans">Q95, Q102, Q50</res>
    <res name="Cheese">Q141, Q222, Q224</res>
    <res name="Eggs">Q40, Q79, Q180</res>
    <res name="Fertilizer">Q103, Q70, Q196</res>
    <res name="Fish">Q146, Q164, Q64</res>
    <res name="Fruit">Q193, Q30, Q104</res>
    <res name="Grain">Q91, Q88, Q147</res>
    <res name="Grapes">Q142, Q69, Q146</res>
    <res name="Herbs">Q218, Q123, Q168</res>
    <res name="Hops">Q90, Q107, Q141</res>
    <res name="Log">Q117, Q181, Q174</res>
    <res name="Milk">Q82, Q107, Q158</res>
    <res name="Nuts">Q136, Q181, Q86</res>
    <res name="Plant Fiber">Q31, Q28, Q88</res>
    <res name="Spices">Q142, Q181, Q128</res>
    <res name="Vegetable">Q150, Q179, Q104</res>
    <res name="Vegetation Density">Q224, Q126, Q127</res>
  </body>
  <body name="System YCIUR Alpha VIar (1)" sectorname="" sectorcoords="309, 1, 5" systemname="YCIUR" systemcoords="3.9, -1.9, -2.2" designation="Alpha" type="Ring" diameter="61500m" zone="Outer" atmosphere="None" timestamp="8/11/2012 6:39:10 PM" outofrange="False">
    <res name="Crystals">Q176 1%</res>
    <res name="Eludium">Q146 54%</res>
    <res name="Gems">Q156 1%</res>
    <res name="Ice">Q73 1%</res>
    <res name="Lumenite">Q196 1%</res>
    <res name="Minerals">Q40 1%</res>
    <res name="Ore">Q88 1%</res>
    <res name="Radioactives">Q71 1%</res>
    <res name="Stone">Q135 1%</res>
    <res name="Antiflux Particles">Q197 1%</res>
    <res name="Sunlight">Q83 30%</res>
  </body>
  <body name="System YCIUR Alpha VIa" sectorname="" sectorcoords="309, 1, 5" systemname="YCIUR" systemcoords="3.9, -1.9, -2.2" designation="Alpha" type="Moon" diameter="3800m" zone="Outer" atmosphere="No Atmosphere" timestamp="8/11/2012 6:39:10 PM" outofrange="False">
    <res name="Coal">Q196 1%</res>
    <res name="Crystals">Q196 1%</res>
    <res name="Eludium">Q182 48%</res>
    <res name="Gems">Q7 1%</res>
    <res name="Ice">Q102 1%</res>
    <res name="Lumenite">Q158 1%</res>
    <res name="Minerals">Q177 1%</res>
    <res name="Natural Gas">Q84 1%</res>
    <res name="Oil">Q132 1%</res>
    <res name="Ore">Q119 1%</res>
    <res name="Radioactives">Q156 1%</res>
    <res name="Stone">Q68 1%</res>
    <res name="Sunlight">Q65 30%</res>
    <res name="Animal Carcass">Q62</res>
    <res name="Beans">Q63</res>
    <res name="Cheese">Q122</res>
    <res name="Eggs">Q174</res>
    <res name="Fertilizer">Q105</res>
    <res name="Fruit">Q130</res>
    <res name="Grain">Q183</res>
    <res name="Grapes">Q186</res>
    <res name="Herbs">Q24</res>
    <res name="Hops">Q142</res>
    <res name="Log">Q151</res>
    <res name="Milk">Q155</res>
    <res name="Nuts">Q124</res>
    <res name="Plant Fiber">Q59</res>
    <res name="Spices">Q154</res>
    <res name="Vegetable">Q96</res>
    <res name="Vegetation Density">Q107</res>
  </body>
  <body name="System YCIUR Alpha VII" sectorname="" sectorcoords="309, 1, 5" systemname="YCIUR" systemcoords="3.9, -1.9, -2.2" designation="Alpha" type="Gas Giant" diameter="56800m" zone="Frigid" atmosphere="Corrosive" timestamp="8/11/2012 6:39:10 PM" outofrange="False">
    <res name="Air">Q76 91%</res>
    <res name="Borexino Precipitate">Q244 2%</res>
    <res name="Cryozine">Q80 3%</res>
    <res name="Hydrogen">Q90 91%</res>
    <res name="Sunlight">Q129 10%</res>
  </body>
  <body name="System YCIUR Alpha VIIa" sectorname="" sectorcoords="309, 1, 5" systemname="YCIUR" systemcoords="3.9, -1.9, -2.2" designation="Alpha" type="Large Moon" diameter="15200m" zone="Frigid" atmosphere="Standard" timestamp="8/11/2012 6:39:10 PM" outofrange="False">
    <res name="Bolite">Q220 1%, Q172 1%, Q168 1%</res>
    <res name="Coal">Q191 1%, Q134 1%, Q167 1%</res>
    <res name="Crystals">Q142 1%, Q129 1%, Q142 1%</res>
    <res name="Gems">Q189 1%, Q13 1%, Q120 1%</res>
    <res name="Ice">Q41 17%, Q129 23%, Q207 8%</res>
    <res name="Lumenite">Q175 1%, Q30 1%, Q117 1%</res>
    <res name="Minerals">Q198 1%, Q171 1%, Q117 1%</res>
    <res name="Natural Gas">Q133 1%, Q180 1%, Q142 1%</res>
    <res name="Oil">Q92 1%, Q138 1%, Q176 1%</res>
    <res name="Ore">Q89 1%, Q74 1%, Q184 1%</res>
    <res name="Radioactives">Q179 1%, Q209 1%, Q82 1%</res>
    <res name="Stone">Q49 1%, Q108 1%, Q191 2%</res>
    <res name="Myrathane">Q69 98%</res>
    <res name="Air">Q131 89%</res>
    <res name="Hydrogen">Q144 89%</res>
    <res name="Sunlight">Q146 10%</res>
    <res name="Animal Carcass">Q168, Q185, Q121</res>
    <res name="Beans">Q135, Q90, Q171</res>
    <res name="Cheese">Q124, Q97, Q138</res>
    <res name="Eggs">Q137, Q198, Q75</res>
    <res name="Fertilizer">Q42, Q127, Q52</res>
    <res name="Fruit">Q165, Q149, Q80</res>
    <res name="Grain">Q120, Q208, Q219</res>
    <res name="Grapes">Q237, Q44, Q196</res>
    <res name="Herbs">Q53, Q142, Q213</res>
    <res name="Hops">Q36, Q182, Q163</res>
    <res name="Log">Q63, Q183, Q124</res>
    <res name="Milk">Q105, Q187, Q82</res>
    <res name="Nuts">Q74, Q54, Q161</res>
    <res name="Plant Fiber">Q43, Q71, Q116</res>
    <res name="Spices">Q151, Q31, Q145</res>
    <res name="Vegetable">Q159, Q90, Q99</res>
    <res name="Vegetation Density">Q123, Q48, Q128</res>
  </body>
  <body name="System YCIUR Alpha VIIb" sectorname="" sectorcoords="309, 1, 5" systemname="YCIUR" systemcoords="3.9, -1.9, -2.2" designation="Alpha" type="Moon" diameter="3800m" zone="Frigid" atmosphere="No Atmosphere" timestamp="8/11/2012 6:39:10 PM" outofrange="False">
    <res name="Coal">Q180 1%</res>
    <res name="Crystals">Q123 1%</res>
    <res name="Eludium">Q120 50%</res>
    <res name="Gems">Q192 1%</res>
    <res name="Ice">Q234 1%</res>
    <res name="Lumenite">Q72 1%</res>
    <res name="Minerals">Q125 1%</res>
    <res name="Natural Gas">Q161 1%</res>
    <res name="Oil">Q77 1%</res>
    <res name="Ore">Q141 1%</res>
    <res name="Radioactives">Q153 1%</res>
    <res name="Stone">Q242 1%</res>
    <res name="Sunlight">Q164 10%</res>
    <res name="Animal Carcass">Q94</res>
    <res name="Beans">Q77</res>
    <res name="Cheese">Q136</res>
    <res name="Eggs">Q193</res>
    <res name="Fertilizer">Q125</res>
    <res name="Fruit">Q137</res>
    <res name="Grain">Q126</res>
    <res name="Grapes">Q206</res>
    <res name="Herbs">Q242</res>
    <res name="Hops">Q212</res>
    <res name="Log">Q226</res>
    <res name="Milk">Q111</res>
    <res name="Nuts">Q233</res>
    <res name="Plant Fiber">Q83</res>
    <res name="Spices">Q88</res>
    <res name="Vegetable">Q88</res>
    <res name="Vegetation Density">Q135</res>
  </body>
  <body name="System YCIUR Alpha VIII" sectorname="" sectorcoords="309, 1, 5" systemname="YCIUR" systemcoords="3.9, -1.9, -2.2" designation="Alpha" type="Gas Giant" diameter="72000m" zone="Frigid" atmosphere="Exotic" timestamp="8/11/2012 6:39:10 PM" outofrange="False">
    <res name="Air">Q82 95%</res>
    <res name="Borexino Precipitate">Q82 2%</res>
    <res name="Cryozine">Q140 2%</res>
    <res name="Hydrogen">Q200 95%</res>
    <res name="Sunlight">Q118 10%</res>
  </body>
  <body name="System YCIUR Alpha VIIIa" sectorname="" sectorcoords="309, 1, 5" systemname="YCIUR" systemcoords="3.9, -1.9, -2.2" designation="Alpha" type="Large Moon" diameter="11400m" zone="Frigid" atmosphere="Standard" timestamp="8/11/2012 6:39:10 PM" outofrange="False">
    <res name="Bolite">Q174 1%, None, Q81 1%</res>
    <res name="Coal">Q71 1%, Q95 1%, Q170 1%</res>
    <res name="Crystals">Q116 1%, Q146 1%, Q90 1%</res>
    <res name="Gems">Q66 1%, Q56 1%, Q246 1%</res>
    <res name="Ice">Q223 7%, Q181 8%, Q62 11%</res>
    <res name="Lumenite">Q214 1%, Q157 1%, Q97 1%</res>
    <res name="Minerals">Q148 1%, Q72 1%, Q65 1%</res>
    <res name="Natural Gas">Q116 1%, Q98 1%, Q155 1%</res>
    <res name="Oil">Q96 1%, Q153 1%, Q183 1%</res>
    <res name="Ore">Q174 1%, Q169 1%, Q150 1%</res>
    <res name="Polytaride">Q170 1%, Q137 1%, None</res>
    <res name="Radioactives">Q89 1%, Q181 1%, Q176 1%</res>
    <res name="Stone">Q206 2%, Q153 2%, Q122 2%</res>
    <res name="Myrathane">Q124 64%</res>
    <res name="Air">Q137 68%</res>
    <res name="Hydrogen">Q125 68%</res>
    <res name="Sunlight">Q136 10%</res>
    <res name="Animal Carcass">Q146, Q176, Q215</res>
    <res name="Beans">Q212, Q140, Q111</res>
    <res name="Cheese">Q174, Q145, Q148</res>
    <res name="Eggs">Q138, Q159, Q189</res>
    <res name="Fertilizer">Q53, Q164, Q108</res>
    <res name="Fruit">Q142, Q67, Q64</res>
    <res name="Grain">Q208, Q241, Q103</res>
    <res name="Grapes">Q63, Q41, Q143</res>
    <res name="Herbs">Q142, Q160, Q166</res>
    <res name="Hops">Q210, Q106, Q97</res>
    <res name="Log">Q161, Q142, Q70</res>
    <res name="Milk">Q174, Q197, Q27</res>
    <res name="Nuts">Q119, Q38, Q119</res>
    <res name="Plant Fiber">Q90, Q167, Q187</res>
    <res name="Spices">Q155, Q69, Q68</res>
    <res name="Vegetable">Q71, Q106, Q190</res>
    <res name="Vegetation Density">Q152, Q235, Q127</res>
  </body>
  <body name="System YCIUR Alpha IX" sectorname="" sectorcoords="309, 1, 5" systemname="YCIUR" systemcoords="3.9, -1.9, -2.2" designation="Alpha" type="Planet" diameter="13300m" zone="Frigid" atmosphere="Exotic" timestamp="8/11/2012 6:39:10 PM" outofrange="False">
    <res name="Bolite">Q84 1%, None, Q122 1%</res>
    <res name="Coal">Q189 1%, Q79 1%, Q103 1%</res>
    <res name="Crystals">Q75 1%, Q89 1%, Q126 1%</res>
    <res name="Gems">Q97 2%, Q132 1%, Q66 1%</res>
    <res name="Ice">Q231 11%, Q25 15%, Q101 7%</res>
    <res name="Lumenite">Q112 1%, Q94 1%, Q85 1%</res>
    <res name="Minerals">Q62 1%, Q165 1%, Q174 1%</res>
    <res name="Natural Gas">Q109 1%, Q143 1%, Q103 1%</res>
    <res name="Oil">Q54 1%, Q98 1%, Q129 1%</res>
    <res name="Ore">Q108 1%, Q190 1%, Q218 1%</res>
    <res name="Polytaride">None, Q106 1%, Q95 1%</res>
    <res name="Radioactives">Q125 1%, Q225 1%, Q98 1%</res>
    <res name="Stone">Q106 2%, Q125 1%, Q41 2%</res>
    <res name="Myrathane">Q76 69%</res>
    <res name="Air">Q94 98%</res>
    <res name="Cryozine">Q144 2%</res>
    <res name="Hydrogen">Q239 98%</res>
    <res name="Sunlight">Q94 10%</res>
    <res name="Animal Carcass">Q136, Q131, Q119</res>
    <res name="Beans">Q183, Q115, Q202</res>
    <res name="Cheese">Q85, Q134, Q164</res>
    <res name="Eggs">Q101, Q32, Q88</res>
    <res name="Fertilizer">Q176, Q129, Q167</res>
    <res name="Fruit">Q125, Q193, Q130</res>
    <res name="Grain">Q101, Q137, Q97</res>
    <res name="Grapes">Q73, Q117, Q60</res>
    <res name="Herbs">Q126, Q148, Q214</res>
    <res name="Hops">Q144, Q143, Q168</res>
    <res name="Log">Q215, Q137, Q90</res>
    <res name="Milk">Q91, Q75, Q167</res>
    <res name="Nuts">Q110, Q194, Q188</res>
    <res name="Plant Fiber">Q179, Q98, Q91</res>
    <res name="Spices">Q88, Q33, Q98</res>
    <res name="Vegetable">Q113, Q215, Q208</res>
    <res name="Vegetation Density">Q90, Q82, Q64</res>
  </body>
  <body name="System YCIUR Alpha IXa" sectorname="" sectorcoords="309, 1, 5" systemname="YCIUR" systemcoords="3.9, -1.9, -2.2" designation="Alpha" type="Moon" diameter="1900m" zone="Frigid" atmosphere="No Atmosphere" timestamp="8/11/2012 6:39:10 PM" outofrange="False">
    <res name="Coal">Q178 1%</res>
    <res name="Crystals">Q54 1%</res>
    <res name="Eludium">Q99 52%</res>
    <res name="Gems">Q126 1%</res>
    <res name="Ice">Q194 1%</res>
    <res name="Lumenite">Q214 1%</res>
    <res name="Minerals">Q150 1%</res>
    <res name="Natural Gas">Q37 1%</res>
    <res name="Oil">Q114 1%</res>
    <res name="Ore">Q105 1%</res>
    <res name="Radioactives">Q152 1%</res>
    <res name="Stone">Q44 1%</res>
    <res name="Sunlight">Q239 10%</res>
    <res name="Animal Carcass">Q190</res>
    <res name="Beans">Q125</res>
    <res name="Cheese">Q98</res>
    <res name="Eggs">Q155</res>
    <res name="Fertilizer">Q131</res>
    <res name="Fruit">Q96</res>
    <res name="Grain">Q106</res>
    <res name="Grapes">Q42</res>
    <res name="Herbs">Q186</res>
    <res name="Hops">Q65</res>
    <res name="Log">Q122</res>
    <res name="Milk">Q224</res>
    <res name="Nuts">Q141</res>
    <res name="Plant Fiber">Q91</res>
    <res name="Spices">Q151</res>
    <res name="Vegetable">Q171</res>
    <res name="Vegetation Density">Q101</res>
  </body>
</database>